Workbook

Sheet Panel
A1: Panimavida 13,2 kV - Ventana de arbitraje
A2: Calculadora de decision: operar a costo marginal (spot) vs. contratar. BESS 9 MW / 36 MWh. Ancla de mercado: ultimos 12 meses completos del nodo (23-may-2025 a 22-may-2026, 365 dias reales del Coordinador Electrico Nacional). Las celdas en azul son editables; el resto son formulas.
A4: LA PREGUNTA DEL COMITE
A5: Conviene ir a costo marginal en vez de firmar un PPA, y hasta cuando?
A7: RESPUESTA EN TRES CIFRAS
A8: Margen bruto - ultimos 12 meses reales | B8: =Margen_DSCR!$B$7 | C8: US$/ano | D8: Ciclando ~340 veces al ano sobre precios reales del nodo. No es proyeccion: es lo que el nodo pago.
A9: Spread necesario para pagar la deuda | B9: =Break_even!$E$8 | C9: USD/MWh | D9: A 340 ciclos y un servicio de deuda de US$400 mil. Contra un spread observado de 77,5 USD/MWh.
A10: Ano en que el escenario elegido cruza ese umbral | B10: =Margen_DSCR!$B$33 | C10: ano | D10: Antes de ese ano el spot domina. Ese es el borde de la ventana.
A12: PALANCAS EDITABLES
A13: Palanca | B13: Valor | C13: Unidad | D13: Nota
A14: Escenario activo (A / B / C) | B14: B | C14: - | D14: A = ventana amplia. B = base. C = estres tipo NEM. Cambia toda la proyeccion.
A15: Ciclos completos por ano | B15: 340 | C15: ciclos | D15: ~0,93 por dia. En la ventana ancla, 88% de los dias tuvo spread mayor a 40 USD/MWh.
A16: CAPEX total | B16: - | C16: MUSD | D16: REEMPLAZAR con el dato real del proyecto.
A17: Deuda / CAPEX | B17: - | C17: % | D17: REEMPLAZAR con el gearing del term sheet.
A18: Tasa de interes | B18: - | C18: % | D18: REEMPLAZAR.
A19: Plazo de la deuda | B19: - | C19: anos | D19: REEMPLAZAR.
A20: DSCR minimo exigido | B20: - | C20: x | D20: REEMPLAZAR con el covenant del term sheet.
A22: Los cinco supuestos financieros estan vacios a proposito. Ninguna cifra de DSCR de este libro es valida hasta que se reemplacen por los terminos reales del term sheet. El resto del modelo -margen, spread, break-even y escenarios- no depende de ellos y ya es valido.
A24: LO QUE ESTE LIBRO DEMUESTRA
A25: 1. El precio de venta nocturno NO viene cayendo: esta plano en 98-100 USD/MWh desde hace tres anos (ventanas de 12 meses completos: 108,2 / 98,2 / 99,6).
A26: 2. Lo que comprimio el spread fue el COSTO DE CARGA, que subio de 10,1 a 22,1 USD/MWh en la ultima ventana, y que oscila con la hidrologia sin tendencia monotona (8,1 en 2024; 24,0 en 2025; 9,6 en ene-may 2026).
A27: 3. Kimal-Lo Aguirre actua sobre el costo marginal DIURNO, es decir sobre el lado que hoy es el riesgo real, y lo empuja a la baja. En la evidencia disponible esa linea es viento de cola, no de frente.
A28: 4. En 1.586 dias de registro, el precio de venta de las 4 horas de punta estuvo en o sobre 50 USD/MWh el 99,2% de los dias.

Sheet Supuestos
A1: Supuestos
A2: Azul = editable. Cada supuesto de mercado esta anclado en dato real del nodo o en fuente citada. Rojo = falta el dato y bloquea el calculo de DSCR.
A4: Supuesto | B4: Valor | C4: Unidad | D4: Fuente / justificacion
A5: TECNICOS
A6: Potencia del BESS | B6: 9 | C6: MW | D6: Ficha de proyecto
A7: Capacidad de almacenamiento | B7: 36 | C7: MWh | D7: Ficha de proyecto (duracion 4 h)
A8: Energia de carga por ciclo | B8: 36 | C8: MWh | D8: Igual a la capacidad
A9: Eficiencia round-trip | B9: 0.83 | C9: - | D9: Conservadora frente al 88% nominal
A10: Energia de venta por ciclo | B10: =$B$8*$B$9 | C10: MWh | D10: Carga x eficiencia
A11: Degradacion anual de capacidad | B11: 0.02 | C11: /ano | D11: Supuesto LFP conservador; ajustar con la garantia del proveedor
A12: ANCLA DE MERCADO - ultimos 12 meses completos
A13: Costo de carga (nivel) | B13: 22.1 | C13: USD/MWh | D13: 365 dias reales, 23-may-2025 a 22-may-2026. Incluye la hidrologia alta de 2025, por lo que es conservador
A14: Precio de venta 4 h punta (nivel) | B14: 99.6 | C14: USD/MWh | D14: Misma ventana de 365 dias
A15: Spread | B15: =$B$14-$B$13 | C15: USD/MWh | D15: Venta menos carga
A16: Piso de venta observado | B16: 50 | C16: USD/MWh | D16: El 99,2% de los 1.586 dias del registro estuvo en o sobre este nivel
A17: Techo de carga en el modelo | B17: 40 | C17: USD/MWh | D17: Limite superior asumido. El maximo anual observado fue 45,0 USD/MWh en 2022
A18: OPERACION
A19: Umbral de spread para ciclar | B19: 20 | C19: USD/MWh | D19: Bajo este umbral no se cicla. El margen es casi insensible al umbral entre 0 y 30
A20: OPEX anual | B20: - | C20: kUSD/ano | D20: O&M, servicio de pronostico day-ahead, seguros y cargos del Coordinador. REEMPLAZAR
A21: Reserva de degradacion | B21: - | C21: kUSD/ano | D21: Augmentation o reposicion de celdas. REEMPLAZAR

Sheet Historico_Ancla
A1: Historico del nodo - por que el ancla son 12 meses completos
A2: Un ano calendario parcial mezcla estacionalidad y no es comparable. Las ventanas de 12 meses completos si lo son, y son la base de la proyeccion. 1.586 dias reales del Coordinador Electrico Nacional.
A4: A. VENTANAS DE 12 MESES COMPLETOS - la serie limpia
A5: Ventana | B5: Carga | C5: Venta | D5: Spread | E5: Delta carga | F5: Delta venta | G5: Delta spread
A6: 23-may-2022 a 22-may-2023 | B6: 37.7 | C6: 200 | D6: 162.3
A7: 23-may-2023 a 22-may-2024 | B7: 12.3 | C7: 108.2 | D7: 96 | E7: -25.4 | F7: -91.8 | G7: -66.4
A8: 23-may-2024 a 22-may-2025 | B8: 10.1 | C8: 98.2 | D8: 88.1 | E8: -2.1 | F8: -10 | G8: -7.9
A9: 23-may-2025 a 22-may-2026 | B9: 22.1 | C9: 99.6 | D9: 77.5 | E9: 12 | F9: 1.4 | G9: ANCLA DEL MODELO
A11: LECTURA CENTRAL - el lado venta esta plano; el que se movio es el lado carga:
A12: Venta: 108,2 / 98,2 / 99,6 USD/MWh en las ultimas tres ventanas. Variacion neta de -8,6 en dos anos, y +1,4 en la ultima.
A13: Carga: 12,3 / 10,1 / 22,1 USD/MWh. Subio 12,0 en la ultima ventana, y eso explica practicamente toda la compresion reciente del spread.
A14: Implicancia: el riesgo del proyecto no es que caiga el precio de venta nocturno. Es que suba el costo de cargar de dia.
A16: B. LA CARGA TIENE TENDENCIA O ES HIDROLOGIA?
A17: Ano calendario | B17: Carga | C17: Venta | D17: Spread | E17: Carga ene-may | G17: Nota
A18: 2022 | B18: 45 | C18: 184.8 | D18: 139.8 | E18: 49.1 | G18: Previo a la saturacion solar
A19: 2023 | B19: 19.9 | C19: 143.1 | D19: 123.3 | E19: 31.4 | G19: Pico de la crisis energetica
A20: 2024 | B20: 8.1 | C20: 93.8 | D20: 85.7 | E20: 13.4 | G20: Carga minima del registro
A21: 2025 | B21: 24 | C21: 113 | D21: 89 | E21: 15.6 | G21: Hidrologia alta: la carga sube
A22: 2026 | B22: 9.6 | C22: 85 | D22: 75.4 | E22: 9.6 | G22: Parcial (ene a 22-may). La carga vuelve a bajar
A24: La carga oscila entre 8,1 y 45,0 USD/MWh sin tendencia monotona: 8,1 (2024), 24,0 (2025), 9,6 (ene-may 2026). El alza de 2025 es consistente con mayor hidrologia -menos vertimiento, menos horas a costo cero- y ya revirtio. El modelo trata el alza del costo de carga como riesgo estructural de largo plazo, no como tendencia ya instalada.
A26: C. PISO DEL PRECIO DE VENTA - registro completo, 1.586 dias
A27: Umbral | B27: Dias bajo el umbral | C27: % del registro | D27: % en o sobre el umbral
A28: venta menor a 40 USD/MWh | B28: 4 | C28: 0.003 | D28: 0.997
A29: venta menor a 50 USD/MWh | B29: 12 | C29: 0.008 | D29: 0.992
A30: venta menor a 55 USD/MWh | B30: 30 | C30: 0.019 | D30: 0.981
A31: venta menor a 60 USD/MWh | B31: 87 | C31: 0.055 | D31: 0.945
A32: venta menor a 70 USD/MWh | B32: 263 | C32: 0.166 | D32: 0.834
A34: Precision obligatoria: el minimo absoluto del registro es 0,0 USD/MWh (30-oct-2022), un dia atipico. La afirmacion correcta y verificable es que el 99,2% de los 1.586 dias tuvo precio de venta en o sobre 50 USD/MWh. En la ventana ancla el peor dia fue 48,8 y el percentil 10 fue 58,5 USD/MWh.

Sheet Escenarios
A1: Escenarios de compresion - una sola variable
A2: La variable que manda es la velocidad con que el almacenamiento del SEN llega a comprimir el nodo del Maule. Se modela por los DOS lados, como advirtio el asesor tecnico: la venta baja y la carga sube.
A4: PARAMETROS DE CADA ESCENARIO (editables)
A5: Escenario | B5: Ano inicio compresion | C5: Delta venta anual | D5: Delta carga anual | E5: Justificacion
A6: A. Ventana amplia | B6: 2031 | C6: -2 | D6: 1 | E6: El almacenamiento sigue concentrado en el norte (86% de los MW en construccion) y la CNE proyecta desacople del sur hacia 2032.
A7: B. Base | B7: 2029 | C7: -4 | D7: 2.5 | E7: Compresion gradual desde la entrada de Kimal-Lo Aguirre (2029-2030) y llegada parcial de BESS al centro-sur.
A8: C. Estres tipo NEM | B8: 2027 | C8: -10 | D8: 5 | E8: Replica el precedente australiano: spread -85% en un ano al pasar la flota BESS de 4.360 a 9.000 MW.
A10: PROYECCION - precio de venta (USD/MWh)
A11: Escenario | B11: 2027 | C11: 2028 | D11: 2029 | E11: 2030 | F11: 2031 | G11: 2032 | H11: 2033 | I11: 2034 | J11: 2035
A12: Escenario A | B12: =MAX(Supuestos!$B$16,Supuestos!$B$14+IF(2027<$B$6,0,(2027-$B$6+1)*$C$6)) | C12: =MAX(Supuestos!$B$16,Supuestos!$B$14+IF(2028<$B$6,0,(2028-$B$6+1)*$C$6)) | D12: =MAX(Supuestos!$B$16,Supuestos!$B$14+IF(2029<$B$6,0,(2029-$B$6+1)*$C$6)) | E12: =MAX(Supuestos!$B$16,Supuestos!$B$14+IF(2030<$B$6,0,(2030-$B$6+1)*$C$6)) | F12: =MAX(Supuestos!$B$16,Supuestos!$B$14+IF(2031<$B$6,0,(2031-$B$6+1)*$C$6)) | G12: =MAX(Supuestos!$B$16,Supuestos!$B$14+IF(2032<$B$6,0,(2032-$B$6+1)*$C$6)) | H12: =MAX(Supuestos!$B$16,Supuestos!$B$14+IF(2033<$B$6,0,(2033-$B$6+1)*$C$6)) | I12: =MAX(Supuestos!$B$16,Supuestos!$B$14+IF(2034<$B$6,0,(2034-$B$6+1)*$C$6)) | J12: =MAX(Supuestos!$B$16,Supuestos!$B$14+IF(2035<$B$6,0,(2035-$B$6+1)*$C$6))
A13: Escenario B | B13: =MAX(Supuestos!$B$16,Supuestos!$B$14+IF(2027<$B$7,0,(2027-$B$7+1)*$C$7)) | C13: =MAX(Supuestos!$B$16,Supuestos!$B$14+IF(2028<$B$7,0,(2028-$B$7+1)*$C$7)) | D13: =MAX(Supuestos!$B$16,Supuestos!$B$14+IF(2029<$B$7,0,(2029-$B$7+1)*$C$7)) | E13: =MAX(Supuestos!$B$16,Supuestos!$B$14+IF(2030<$B$7,0,(2030-$B$7+1)*$C$7)) | F13: =MAX(Supuestos!$B$16,Supuestos!$B$14+IF(2031<$B$7,0,(2031-$B$7+1)*$C$7)) | G13: =MAX(Supuestos!$B$16,Supuestos!$B$14+IF(2032<$B$7,0,(2032-$B$7+1)*$C$7)) | H13: =MAX(Supuestos!$B$16,Supuestos!$B$14+IF(2033<$B$7,0,(2033-$B$7+1)*$C$7)) | I13: =MAX(Supuestos!$B$16,Supuestos!$B$14+IF(2034<$B$7,0,(2034-$B$7+1)*$C$7)) | J13: =MAX(Supuestos!$B$16,Supuestos!$B$14+IF(2035<$B$7,0,(2035-$B$7+1)*$C$7))
A14: Escenario C | B14: =MAX(Supuestos!$B$16,Supuestos!$B$14+IF(2027<$B$8,0,(2027-$B$8+1)*$C$8)) | C14: =MAX(Supuestos!$B$16,Supuestos!$B$14+IF(2028<$B$8,0,(2028-$B$8+1)*$C$8)) | D14: =MAX(Supuestos!$B$16,Supuestos!$B$14+IF(2029<$B$8,0,(2029-$B$8+1)*$C$8)) | E14: =MAX(Supuestos!$B$16,Supuestos!$B$14+IF(2030<$B$8,0,(2030-$B$8+1)*$C$8)) | F14: =MAX(Supuestos!$B$16,Supuestos!$B$14+IF(2031<$B$8,0,(2031-$B$8+1)*$C$8)) | G14: =MAX(Supuestos!$B$16,Supuestos!$B$14+IF(2032<$B$8,0,(2032-$B$8+1)*$C$8)) | H14: =MAX(Supuestos!$B$16,Supuestos!$B$14+IF(2033<$B$8,0,(2033-$B$8+1)*$C$8)) | I14: =MAX(Supuestos!$B$16,Supuestos!$B$14+IF(2034<$B$8,0,(2034-$B$8+1)*$C$8)) | J14: =MAX(Supuestos!$B$16,Supuestos!$B$14+IF(2035<$B$8,0,(2035-$B$8+1)*$C$8))
A16: PROYECCION - costo de carga (USD/MWh)
A17: Escenario | B17: 2027 | C17: 2028 | D17: 2029 | E17: 2030 | F17: 2031 | G17: 2032 | H17: 2033 | I17: 2034 | J17: 2035
A18: Escenario A | B18: =MIN(Supuestos!$B$17,Supuestos!$B$13+IF(2027<$B$6,0,(2027-$B$6+1)*$D$6)) | C18: =MIN(Supuestos!$B$17,Supuestos!$B$13+IF(2028<$B$6,0,(2028-$B$6+1)*$D$6)) | D18: =MIN(Supuestos!$B$17,Supuestos!$B$13+IF(2029<$B$6,0,(2029-$B$6+1)*$D$6)) | E18: =MIN(Supuestos!$B$17,Supuestos!$B$13+IF(2030<$B$6,0,(2030-$B$6+1)*$D$6)) | F18: =MIN(Supuestos!$B$17,Supuestos!$B$13+IF(2031<$B$6,0,(2031-$B$6+1)*$D$6)) | G18: =MIN(Supuestos!$B$17,Supuestos!$B$13+IF(2032<$B$6,0,(2032-$B$6+1)*$D$6)) | H18: =MIN(Supuestos!$B$17,Supuestos!$B$13+IF(2033<$B$6,0,(2033-$B$6+1)*$D$6)) | I18: =MIN(Supuestos!$B$17,Supuestos!$B$13+IF(2034<$B$6,0,(2034-$B$6+1)*$D$6)) | J18: =MIN(Supuestos!$B$17,Supuestos!$B$13+IF(2035<$B$6,0,(2035-$B$6+1)*$D$6))
A19: Escenario B | B19: =MIN(Supuestos!$B$17,Supuestos!$B$13+IF(2027<$B$7,0,(2027-$B$7+1)*$D$7)) | C19: =MIN(Supuestos!$B$17,Supuestos!$B$13+IF(2028<$B$7,0,(2028-$B$7+1)*$D$7)) | D19: =MIN(Supuestos!$B$17,Supuestos!$B$13+IF(2029<$B$7,0,(2029-$B$7+1)*$D$7)) | E19: =MIN(Supuestos!$B$17,Supuestos!$B$13+IF(2030<$B$7,0,(2030-$B$7+1)*$D$7)) | F19: =MIN(Supuestos!$B$17,Supuestos!$B$13+IF(2031<$B$7,0,(2031-$B$7+1)*$D$7)) | G19: =MIN(Supuestos!$B$17,Supuestos!$B$13+IF(2032<$B$7,0,(2032-$B$7+1)*$D$7)) | H19: =MIN(Supuestos!$B$17,Supuestos!$B$13+IF(2033<$B$7,0,(2033-$B$7+1)*$D$7)) | I19: =MIN(Supuestos!$B$17,Supuestos!$B$13+IF(2034<$B$7,0,(2034-$B$7+1)*$D$7)) | J19: =MIN(Supuestos!$B$17,Supuestos!$B$13+IF(2035<$B$7,0,(2035-$B$7+1)*$D$7))
A20: Escenario C | B20: =MIN(Supuestos!$B$17,Supuestos!$B$13+IF(2027<$B$8,0,(2027-$B$8+1)*$D$8)) | C20: =MIN(Supuestos!$B$17,Supuestos!$B$13+IF(2028<$B$8,0,(2028-$B$8+1)*$D$8)) | D20: =MIN(Supuestos!$B$17,Supuestos!$B$13+IF(2029<$B$8,0,(2029-$B$8+1)*$D$8)) | E20: =MIN(Supuestos!$B$17,Supuestos!$B$13+IF(2030<$B$8,0,(2030-$B$8+1)*$D$8)) | F20: =MIN(Supuestos!$B$17,Supuestos!$B$13+IF(2031<$B$8,0,(2031-$B$8+1)*$D$8)) | G20: =MIN(Supuestos!$B$17,Supuestos!$B$13+IF(2032<$B$8,0,(2032-$B$8+1)*$D$8)) | H20: =MIN(Supuestos!$B$17,Supuestos!$B$13+IF(2033<$B$8,0,(2033-$B$8+1)*$D$8)) | I20: =MIN(Supuestos!$B$17,Supuestos!$B$13+IF(2034<$B$8,0,(2034-$B$8+1)*$D$8)) | J20: =MIN(Supuestos!$B$17,Supuestos!$B$13+IF(2035<$B$8,0,(2035-$B$8+1)*$D$8))
A22: PROYECCION - spread (USD/MWh)
A23: Escenario | B23: 2027 | C23: 2028 | D23: 2029 | E23: 2030 | F23: 2031 | G23: 2032 | H23: 2033 | I23: 2034 | J23: 2035
A24: Escenario A | B24: =B12-B18 | C24: =C12-C18 | D24: =D12-D18 | E24: =E12-E18 | F24: =F12-F18 | G24: =G12-G18 | H24: =H12-H18 | I24: =I12-I18 | J24: =J12-J18
A25: Escenario B | B25: =B13-B19 | C25: =C13-C19 | D25: =D13-D19 | E25: =E13-E19 | F25: =F13-F19 | G25: =G13-G19 | H25: =H13-H19 | I25: =I13-I19 | J25: =J13-J19
A26: Escenario C | B26: =B14-B20 | C26: =C14-C20 | D26: =D14-D20 | E26: =E14-E20 | F26: =F14-F20 | G26: =G14-G20 | H26: =H14-H20 | I26: =I14-I20 | J26: =J14-J20
A28: El piso de venta (50 USD/MWh) y el techo de carga (40 USD/MWh) acotan la proyeccion: el spread no cae indefinidamente porque el precio nocturno lo fija el costo variable de la ultima unidad termica que entra al anochecer, no el sol. Ese piso esta calibrado sobre el 99,2% del registro historico.

Sheet Margen_DSCR
A1: Margen y cobertura de deuda
A2: El margen no depende de los supuestos financieros: se calcula sobre precios y volumenes, y ya es valido. El DSCR si depende, y esta bloqueado hasta que se ingresen los terminos reales del term sheet.
A4: A. VALIDACION CONTRA DATO REAL (sin proyeccion)
A5: Concepto | B5: Valor | C5: Unidad | D5: Como se obtiene
A6: Ciclos en la ventana ancla | B6: 340 | C6: ciclos | D6: Dias con spread mayor a 20 USD/MWh en los ultimos 12 meses completos
A7: Margen bruto de arbitraje | B7: 814738 | C7: US$/ano | D7: Suma dia a dia de venta x 29,88 menos carga x 36, sobre los dias efectivamente ciclados
A8: Margen si se cicla todos los dias | B8: 810174 | C8: US$/ano | D8: 359 ciclos. Practicamente identico: el margen es robusto al criterio de ciclado
A9: Margen a 182 ciclos (plan conservador) | B9: 524363 | C9: US$/ano | D9: Mitad de utilizacion, calculado sobre el ano mas comprimido del registro
A11: UNIFICACION DE CIFRAS - el expediente actual tiene dos numeros distintos y conviene explicar la diferencia antes de que la encuentren: el informe v7 reporta US$493 mil/ano (precio-nivel anual por volumen, a 182 ciclos) y el correo enviado menciona cerca de US$0,9 millones/ano (seleccion dia a dia con ciclado diario). Ambos son correctos bajo su propio metodo. La cifra que este libro propone como titular es US$815 mil/ano: dia a dia, 340 ciclos, sobre los ultimos 12 meses completos y reales.
A13: B. MARGEN BRUTO PROYECTADO POR ESCENARIO (US$/ano)
A14: Escenario | B14: 2027 | C14: 2028 | D14: 2029 | E14: 2030 | F14: 2031 | G14: 2032 | H14: 2033 | I14: 2034 | J14: 2035
A15: Escenario A | B15: =Panel!$B$15*(Escenarios!B12*Supuestos!$B$10*(1-Supuestos!$B$11)^0-Escenarios!B18*Supuestos!$B$8) | C15: =Panel!$B$15*(Escenarios!C12*Supuestos!$B$10*(1-Supuestos!$B$11)^1-Escenarios!C18*Supuestos!$B$8) | D15: =Panel!$B$15*(Escenarios!D12*Supuestos!$B$10*(1-Supuestos!$B$11)^2-Escenarios!D18*Supuestos!$B$8) | E15: =Panel!$B$15*(Escenarios!E12*Supuestos!$B$10*(1-Supuestos!$B$11)^3-Escenarios!E18*Supuestos!$B$8) | F15: =Panel!$B$15*(Escenarios!F12*Supuestos!$B$10*(1-Supuestos!$B$11)^4-Escenarios!F18*Supuestos!$B$8) | G15: =Panel!$B$15*(Escenarios!G12*Supuestos!$B$10*(1-Supuestos!$B$11)^5-Escenarios!G18*Supuestos!$B$8) | H15: =Panel!$B$15*(Escenarios!H12*Supuestos!$B$10*(1-Supuestos!$B$11)^6-Escenarios!H18*Supuestos!$B$8) | I15: =Panel!$B$15*(Escenarios!I12*Supuestos!$B$10*(1-Supuestos!$B$11)^7-Escenarios!I18*Supuestos!$B$8) | J15: =Panel!$B$15*(Escenarios!J12*Supuestos!$B$10*(1-Supuestos!$B$11)^8-Escenarios!J18*Supuestos!$B$8)
A16: Escenario B | B16: =Panel!$B$15*(Escenarios!B13*Supuestos!$B$10*(1-Supuestos!$B$11)^0-Escenarios!B19*Supuestos!$B$8) | C16: =Panel!$B$15*(Escenarios!C13*Supuestos!$B$10*(1-Supuestos!$B$11)^1-Escenarios!C19*Supuestos!$B$8) | D16: =Panel!$B$15*(Escenarios!D13*Supuestos!$B$10*(1-Supuestos!$B$11)^2-Escenarios!D19*Supuestos!$B$8) | E16: =Panel!$B$15*(Escenarios!E13*Supuestos!$B$10*(1-Supuestos!$B$11)^3-Escenarios!E19*Supuestos!$B$8) | F16: =Panel!$B$15*(Escenarios!F13*Supuestos!$B$10*(1-Supuestos!$B$11)^4-Escenarios!F19*Supuestos!$B$8) | G16: =Panel!$B$15*(Escenarios!G13*Supuestos!$B$10*(1-Supuestos!$B$11)^5-Escenarios!G19*Supuestos!$B$8) | H16: =Panel!$B$15*(Escenarios!H13*Supuestos!$B$10*(1-Supuestos!$B$11)^6-Escenarios!H19*Supuestos!$B$8) | I16: =Panel!$B$15*(Escenarios!I13*Supuestos!$B$10*(1-Supuestos!$B$11)^7-Escenarios!I19*Supuestos!$B$8) | J16: =Panel!$B$15*(Escenarios!J13*Supuestos!$B$10*(1-Supuestos!$B$11)^8-Escenarios!J19*Supuestos!$B$8)
A17: Escenario C | B17: =Panel!$B$15*(Escenarios!B14*Supuestos!$B$10*(1-Supuestos!$B$11)^0-Escenarios!B20*Supuestos!$B$8) | C17: =Panel!$B$15*(Escenarios!C14*Supuestos!$B$10*(1-Supuestos!$B$11)^1-Escenarios!C20*Supuestos!$B$8) | D17: =Panel!$B$15*(Escenarios!D14*Supuestos!$B$10*(1-Supuestos!$B$11)^2-Escenarios!D20*Supuestos!$B$8) | E17: =Panel!$B$15*(Escenarios!E14*Supuestos!$B$10*(1-Supuestos!$B$11)^3-Escenarios!E20*Supuestos!$B$8) | F17: =Panel!$B$15*(Escenarios!F14*Supuestos!$B$10*(1-Supuestos!$B$11)^4-Escenarios!F20*Supuestos!$B$8) | G17: =Panel!$B$15*(Escenarios!G14*Supuestos!$B$10*(1-Supuestos!$B$11)^5-Escenarios!G20*Supuestos!$B$8) | H17: =Panel!$B$15*(Escenarios!H14*Supuestos!$B$10*(1-Supuestos!$B$11)^6-Escenarios!H20*Supuestos!$B$8) | I17: =Panel!$B$15*(Escenarios!I14*Supuestos!$B$10*(1-Supuestos!$B$11)^7-Escenarios!I20*Supuestos!$B$8) | J17: =Panel!$B$15*(Escenarios!J14*Supuestos!$B$10*(1-Supuestos!$B$11)^8-Escenarios!J20*Supuestos!$B$8)
A19: Incluye degradacion de capacidad compuesta sobre el volumen de venta. No incluye OPEX ni reserva de degradacion: son margenes brutos de arbitraje, directamente comparables con la cifra real de la seccion A.
A21: C. COBERTURA DE DEUDA
A22: Concepto | B22: Valor | C22: Unidad | D22: Nota
A23: Monto de deuda | B23: =IF(OR(Panel!$B$16="-",Panel!$B$17="-"),"faltan datos",Panel!$B$16*Panel!$B$17) | C23: MUSD | D23: CAPEX por gearing, tomados del Panel
A24: Servicio anual de la deuda | B24: =IF(OR(Panel!$B$18="-",Panel!$B$19="-",$B$23="faltan datos"),"faltan datos",-PMT(Panel!$B$18,Panel!$B$19,$B$23)*1000000) | C24: US$/ano | D24: Cuota constante. Ajustar si hay gracia o perfil sculpted
A25: DSCR con el margen real de la ventana ancla | B25: =IF($B$24="faltan datos","faltan datos",$B$7/$B$24) | D25: Margen bruto sobre servicio. Restar OPEX y reserva para el DSCR definitivo
A27: D. ANO EN QUE EL ESCENARIO CRUZA EL BREAK-EVEN
A28: Escenario activo (tomado del Panel) | B28: =Panel!$B$14
A29: Ano | B29: 2027 | C29: 2028 | D29: 2029 | E29: 2030 | F29: 2031 | G29: 2032 | H29: 2033 | I29: 2034 | J29: 2035
A30: Spread del escenario activo (USD/MWh) | B30: =IF(Panel!$B$14="A",Escenarios!B24,IF(Panel!$B$14="B",Escenarios!B25,Escenarios!B26)) | C30: =IF(Panel!$B$14="A",Escenarios!C24,IF(Panel!$B$14="B",Escenarios!C25,Escenarios!C26)) | D30: =IF(Panel!$B$14="A",Escenarios!D24,IF(Panel!$B$14="B",Escenarios!D25,Escenarios!D26)) | E30: =IF(Panel!$B$14="A",Escenarios!E24,IF(Panel!$B$14="B",Escenarios!E25,Escenarios!E26)) | F30: =IF(Panel!$B$14="A",Escenarios!F24,IF(Panel!$B$14="B",Escenarios!F25,Escenarios!F26)) | G30: =IF(Panel!$B$14="A",Escenarios!G24,IF(Panel!$B$14="B",Escenarios!G25,Escenarios!G26)) | H30: =IF(Panel!$B$14="A",Escenarios!H24,IF(Panel!$B$14="B",Escenarios!H25,Escenarios!H26)) | I30: =IF(Panel!$B$14="A",Escenarios!I24,IF(Panel!$B$14="B",Escenarios!I25,Escenarios!I26)) | J30: =IF(Panel!$B$14="A",Escenarios!J24,IF(Panel!$B$14="B",Escenarios!J25,Escenarios!J26))
A31: Bajo el break-even? (1 = si) | B31: =IF(B30<Break_even!$E$8,1,0) | C31: =IF(C30<Break_even!$E$8,1,0) | D31: =IF(D30<Break_even!$E$8,1,0) | E31: =IF(E30<Break_even!$E$8,1,0) | F31: =IF(F30<Break_even!$E$8,1,0) | G31: =IF(G30<Break_even!$E$8,1,0) | H31: =IF(H30<Break_even!$E$8,1,0) | I31: =IF(I30<Break_even!$E$8,1,0) | J31: =IF(J30<Break_even!$E$8,1,0)
A33: Primer ano con spread bajo el break-even | B33: =IFERROR(INDEX($B$29:$J$29,MATCH(1,$B$31:$J$31,0)),"no cruza hasta 2035") | C33: borde de la ventana
A35: Este es el numero que responde la pregunta del Comite: hasta que ano el spot domina bajo el escenario elegido. Cambiando el escenario en el Panel se ve moverse el borde de la ventana. Las tres filas auxiliares de arriba dejan el calculo a la vista, sin formulas matriciales.

Sheet Break_even
A1: Break-even - cuanto tiene que caer el mercado antes de que duela
A2: Spread minimo necesario para cubrir el servicio de la deuda, segun numero de ciclos. Se lee al revés que un caso base: no dice cuanto se gana, dice cuanta holgura hay.
A4: Spread requerido (USD/MWh) por nivel de servicio de deuda
A5: Servicio de deuda (US$/ano) | B5: 182 ciclos | C5: 250 ciclos | D5: 300 ciclos | E5: 340 ciclos | F5: 365 ciclos
A6: 200000 | B6: =(200000/182+Supuestos!$B$13*Supuestos!$B$8)/Supuestos!$B$10-Supuestos!$B$13 | C6: =(200000/250+Supuestos!$B$13*Supuestos!$B$8)/Supuestos!$B$10-Supuestos!$B$13 | D6: =(200000/300+Supuestos!$B$13*Supuestos!$B$8)/Supuestos!$B$10-Supuestos!$B$13 | E6: =(200000/340+Supuestos!$B$13*Supuestos!$B$8)/Supuestos!$B$10-Supuestos!$B$13 | F6: =(200000/365+Supuestos!$B$13*Supuestos!$B$8)/Supuestos!$B$10-Supuestos!$B$13
A7: 300000 | B7: =(300000/182+Supuestos!$B$13*Supuestos!$B$8)/Supuestos!$B$10-Supuestos!$B$13 | C7: =(300000/250+Supuestos!$B$13*Supuestos!$B$8)/Supuestos!$B$10-Supuestos!$B$13 | D7: =(300000/300+Supuestos!$B$13*Supuestos!$B$8)/Supuestos!$B$10-Supuestos!$B$13 | E7: =(300000/340+Supuestos!$B$13*Supuestos!$B$8)/Supuestos!$B$10-Supuestos!$B$13 | F7: =(300000/365+Supuestos!$B$13*Supuestos!$B$8)/Supuestos!$B$10-Supuestos!$B$13
A8: 400000 | B8: =(400000/182+Supuestos!$B$13*Supuestos!$B$8)/Supuestos!$B$10-Supuestos!$B$13 | C8: =(400000/250+Supuestos!$B$13*Supuestos!$B$8)/Supuestos!$B$10-Supuestos!$B$13 | D8: =(400000/300+Supuestos!$B$13*Supuestos!$B$8)/Supuestos!$B$10-Supuestos!$B$13 | E8: =(400000/340+Supuestos!$B$13*Supuestos!$B$8)/Supuestos!$B$10-Supuestos!$B$13 | F8: =(400000/365+Supuestos!$B$13*Supuestos!$B$8)/Supuestos!$B$10-Supuestos!$B$13 | G8: referencia del Panel
A9: 500000 | B9: =(500000/182+Supuestos!$B$13*Supuestos!$B$8)/Supuestos!$B$10-Supuestos!$B$13 | C9: =(500000/250+Supuestos!$B$13*Supuestos!$B$8)/Supuestos!$B$10-Supuestos!$B$13 | D9: =(500000/300+Supuestos!$B$13*Supuestos!$B$8)/Supuestos!$B$10-Supuestos!$B$13 | E9: =(500000/340+Supuestos!$B$13*Supuestos!$B$8)/Supuestos!$B$10-Supuestos!$B$13 | F9: =(500000/365+Supuestos!$B$13*Supuestos!$B$8)/Supuestos!$B$10-Supuestos!$B$13
A10: 600000 | B10: =(600000/182+Supuestos!$B$13*Supuestos!$B$8)/Supuestos!$B$10-Supuestos!$B$13 | C10: =(600000/250+Supuestos!$B$13*Supuestos!$B$8)/Supuestos!$B$10-Supuestos!$B$13 | D10: =(600000/300+Supuestos!$B$13*Supuestos!$B$8)/Supuestos!$B$10-Supuestos!$B$13 | E10: =(600000/340+Supuestos!$B$13*Supuestos!$B$8)/Supuestos!$B$10-Supuestos!$B$13 | F10: =(600000/365+Supuestos!$B$13*Supuestos!$B$8)/Supuestos!$B$10-Supuestos!$B$13
A12: COMO SE LEE:
A13: El spread observado en la ventana ancla (ultimos 12 meses completos) es 77,5 USD/MWh.
A14: A 340 ciclos, cubrir un servicio de deuda de US$400 mil requiere un spread de 43,9 USD/MWh.
A15: Es decir: el spread tendria que caer un 43% desde el nivel observado antes de comprometer el servicio de la deuda.
A16: En la ventana ancla el percentil 10 del spread diario fue 29,2 USD/MWh y el 88% de los dias supero 40 USD/MWh.
A18: El calculo mantiene el costo de carga en el nivel de la ventana ancla (22,1 USD/MWh), que ya incorpora la hidrologia alta de 2025. Con el costo de carga de 2026 (9,6 USD/MWh) el spread requerido seria todavia menor.

Sheet Gatillos
A1: Sistema de gatillos - de apuesta a politica monitoreada
A2: Convierte la decision en una politica revisable trimestralmente. Cada gatillo tiene metrica, fuente, umbral y accion predefinida. Es la respuesta a la pregunta "y si se equivocan?".
A4: # | B4: Gatillo | C4: Metrica y fuente | D4: Umbral | E4: Valor actual | F4: Accion al activarse
A5: 1 | B5: Compresion del spread | C5: Spread movil 12M del nodo. Coordinador | D5: menor a 55 USD/MWh | E5: 77,5 | F5: Acelerar la negociacion del contrato de venta o del floor nocturno
A6: 2 | B6: Erosion del piso nocturno | C6: Percentil 10 mensual del precio de punta 4 h. Coordinador | D6: menor a 50 USD/MWh | E6: 58,5 | F6: Revisar el caso base y el perfil de amortizacion con el banco
A7: 3 | B7: Alza del costo de carga | C7: Costo de carga movil 12M. Coordinador | D7: mayor a 35 USD/MWh | E7: 22,1 | F7: Reponderar el horizonte de la Fase 1. Es el riesgo que senalo el asesor tecnico
A8: 4 | B8: BESS materializado en el centro-sur | C8: MW en OPERACION en Maule, Nuble y Biobio. Coordinador | D8: mayor a 300 MW | E8: 0 MW registrado | F8: Reevaluar la exposicion locacional y adelantar la contratacion
A9: 5 | B9: Refuerzo de transmision | C9: Entrada en operacion de obra centro-sur o del HVDC. PET de la CNE | D9: obra en servicio | E9: Kimal-Lo Aguirre 2029-30 | F9: Reevaluar el acoplamiento del nodo al troncal
A10: 6 | B10: Cobertura de deuda | C10: DSCR proyectado a 12 meses | D10: bajo el covenant | E10: faltan datos | F10: Activar contratacion parcial de la energia de venta
A12: Los umbrales son propuestas calibradas sobre el registro historico y deben ratificarse con el banco; el del gatillo 6 requiere el covenant del term sheet. Frecuencia de revision: TRIMESTRAL, no anual. El precedente australiano -spread -85% en un ano- demuestra que la compresion puede ser abrupta.

Sheet Instrumentos
A1: Que contrato, y cuando - la distincion que falta en el expediente
A2: El expediente dice "no PPA ahora, reevaluar hacia 2030" y eso suena contradictorio. No lo es: son dos contratos distintos que hoy se llaman igual.
B4: PPA de COMPRA a 28 USD/MWh (la oferta actual) | C4: Instrumento de VENTA (Fase 2, 2030-2032)
A5: Que fija | B5: El precio al que el proyecto COMPRA su energia de carga | C5: El precio al que el proyecto VENDE en la noche
A6: Riesgo que cubre | B6: Que SUBA el precio de compra | C6: Que CAIGA el precio de venta
A7: Es el riesgo real del proyecto? | B7: No. El proyecto es posicion vendedora | C7: Si. Es exactamente el riesgo del activo
A8: Efecto sobre el margen | B8: Lo destruye: cerca de US$83 mil/ano de sobrecosto | C8: Lo estabiliza
A9: Efecto sobre el DSCR | B9: Lo deteriora: agrega costo fijo sin cubrir riesgo | C9: Lo mejora: reduce la volatilidad de caja
A10: VEREDICTO | B10: Rechazar de forma permanente, no "por ahora" | C10: Negociar desde el ano 1; firmar entre 2030 y 2032
A12: POR QUE EL PPA DE COMPRA NO MEJORA CON EL TIEMPO
A13: Mientras persista la saturacion solar diurna, comprar la energia de carga a 28 USD/MWh seguira siendo peor que comprarla a spot. Lo que se reevalua en 2030 NO es esta oferta: es un instrumento distinto. Conviene decirlo asi al Comite, para no dejar la impresion de que el proyecto posterga una decision que en realidad ya tomo.
A15: ADVERTENCIA SOBRE LA FASE 2 - hay que ajustar el lenguaje
A16: La investigacion de mercado no encontro evidencia de PPA ni de tolling para almacenamiento a escala PMG (menos de 10 MW) en Chile. Los contratos verificados son de cientos de MW con contrapartes investment grade: Grenergy con una utility por 1 TWh/ano a 15 anos, y Grenergy con Codelco por 0,5 TWh/ano. Prometer al banco "un PPA en 2032" para 9 MW es una promesa que hoy no tiene mercado que la respalde.
A17: Los instrumentos realistas a esta escala son otros y conviene nombrarlos asi: incorporacion a un portafolio de comercializacion o a un agregador; floor o collar nocturno con un comercializador; tolling con un actor mayor; o el regimen de precio estabilizado, este ultimo con la advertencia del DS 1/2026 que figura en la hoja Fuentes.

Sheet Transmision
A1: La objecion de transmision, contestada con fuentes
A2: Objecion: "Kimal-Lo Aguirre traera energia del norte al sur y hundira el precio de venta nocturno". Cada respuesta esta anclada en fuente publica citable.
A4: Punto | B4: Hecho verificado | C4: Fecha / estado | D4: Fuente
A5: Punto de aterrizaje | B5: La linea va de S/E Kimal (Antofagasta) a S/E Lo Aguirre (Pudahuel, Region Metropolitana). NO llega a la Region del Maule. No existe tramo al sur en este proyecto. | C5: HVDC +-600 kV, 3.000 MW, 1.342 km | D5: Coordinador Electrico Nacional; CNE 04-feb-2026
A6: Cronograma | B6: RCA aprobada 14-nov-2025. Construccion iniciada 4-feb-2026. Operacion comercial estimada mayo 2029; el Informe Final PET2026 de la CNE usa 2030 para el acoplamiento norte-centro. | C6: 2029-2030, con historial de retrasos | D6: CNE; ISA Interchile; La Tercera
A7: Que energia transporta | B7: Su objetivo declarado es evacuar excedente solar y eolico DIURNO del norte hacia el centro. La linea no almacena: transporta flujo en tiempo real. | C7: Verificado en la descripcion de la CNE | D7: CNE; PET2026
A8: Efecto por franja horaria | B8: De noche el norte no tiene excedente solar que exportar. El efecto directo sobre el costo marginal NOCTURNO del centro-sur es estructuralmente menor que el diurno. | C8: INFERENCIA fisica. No hay cifra oficial | D8: No cuantificado en fuente oficial
A9: Topologia del nodo | B9: S/E Panimavida es de 220 kV (linea Ancoa-San Ambrosio). El nodo del BESS, a 13,2 kV, esta aguas abajo. Del troncal de 500 kV lo separan dos escalones de transformacion. | C9: Verificado | D9: CNE Calificacion de Instalaciones; Coordinador EAF 011/2019
A10: El HVDC que si cruza el Maule | B10: Lo Aguirre-Entre Rios (+-600 kV) pasa por el Maule, pero su proposito es evacuar excedente EOLICO DEL SUR hacia el centro-norte: flujo en sentido contrario al que preocupa. Fecha no verificada oficialmente. | C10: Adjudicacion condicionada; fecha NO VERIFICADA | D10: Electromineria; Prieto Abogados; CNE ITP PET2024
A11: Desacople del sur | B11: La CNE proyecta que las diferencias de costo marginal en la zona sur PERSISTEN hacia 2032 incluso con las obras de 500 kV, sin acoplamiento pleno de los costos marginales anuales. | C11: Informe Final PET2026 | D11: CNE / Coordinador, PET2026
A12: Vertimiento creciente | B12: Vertimiento renovable ene-feb 2026: 1.402 GWh, un 29,3% mas que el ano anterior. Confirma que el excedente diurno sigue creciendo, es decir que el lado carga se sigue abaratando. | C12: ene-feb 2026 | D12: Renewables Now; PV-Tech / ACERA
A14: EL GIRO DEL ARGUMENTO - esto es lo que hay que decirle al director
A15: La preocupacion es que Kimal-Lo Aguirre baje el precio de venta nocturno. Pero los datos del propio nodo muestran que el precio de venta nocturno NO viene cayendo: esta plano en 98-100 USD/MWh desde hace tres anos. Lo que si se movio, y comprimio el spread, fue el COSTO DE CARGA diurno, que subio de 10,1 a 22,1 USD/MWh.
A16: Y Kimal-Lo Aguirre actua precisamente sobre el costo marginal diurno, empujandolo A LA BAJA. Sobre la evidencia disponible, la linea que se teme es viento de cola para el riesgo real del proyecto, no viento de frente.
A17: El riesgo verdadero -el que identifico el asesor tecnico- es que el costo de carga suba a medida que baja el vertimiento y las baterias compiten por el excedente del mediodia. Ese riesgo esta explicitado en el gatillo 3.

Sheet Fuentes
A1: Fuentes
A2: Cada dato publicable de este libro tiene fuente. Lo marcado NO VERIFICADO no se publica.
A4: Dato | B4: Fuente | C4: URL
A5: BESS en operacion en el SEN: 2.283 MW / 9.346 MWh (mar-2026) | B5: Coordinador via Electromineria | C5: https://electromineria.cl/potencia-instalada-almacenamiento-sistema-electrico-se-duplicara-2026/
A6: BESS en construccion: 6.358 MW en 74 proyectos (jun-2026) | B6: CNE via Actualidad Juridica | C6: https://actualidadjuridica.doe.cl/proyectos-de-almacenamiento-con-baterias-en-construccion-superan-los-6-300-mw-en-chile/
A7: Distribucion regional del BESS en construccion: Antofagasta 44%, Atacama 23%, Tarapaca 13,6%, RM 5%. El Maule NO figura | B7: CNE (jun-2026) | C7: mismo enlace anterior
A8: NEM Australia: spread -85% en un ano (AU$342 a AU$51/MWh) con flota BESS de 4.360 a 9.000 MW | B8: Energy-Storage.News 29-jul-2026 | C8: https://www.energy-storage.news/nem-battery-price-spreads-fall-85-in-a-year-as-australias-grid-scale-bess-fleet-passes-9000mw/
A9: CAISO: BESS sobre 13 GW y spread TB4 proyectado AL ALZA, a US$240-270/MWh hacia 2030 | B9: Modo Energy feb-2026 | C9: https://modoenergy.com/research/en/caiso-market-outlook-february-2026-california-power-price-spread
A10: Kimal-Lo Aguirre: +-600 kV, 3.000 MW, de Kimal a Lo Aguirre (RM) | B10: Coordinador Electrico Nacional | C10: https://www.coordinador.cl/desarrollo/documentos/grandes-proyectos/proyecto-hvdc-kimal-lo-aguirre/
A11: Inicio de construccion del HVDC: 4-feb-2026 | B11: CNE | C11: https://www.cne.cl/prensa/prensa-2026/02-febrero-2026/cne-participa-en-inicio-de-la-etapa-de-construccion-de-la-linea-de-transmision-hvdc-kimal-lo-aguirre/
A12: El desacople del sur persiste hacia 2032 incluso con las obras de 500 kV | B12: CNE, Informe Final PET2026 | C12: https://www.coordinador.cl/wp-content/uploads/2026/01/Informe-Final-PET2026.pdf
A13: Vertimiento ene-feb 2026: 1.402 GWh, +29,3% interanual | B13: Renewables Now | C13: https://renewablesnow.com/news/chiles-renewables-curtailment-already-at-1-4-twh-in-jan-feb-2026-1292010/
A14: NTCO-PMGD del 19-feb-2026, Capitulo 9: coordinacion de PMGD CON almacenamiento con el Coordinador | B14: CNE | C14: https://www.cne.cl/wp-content/uploads/2026/02/2026.02.19_NTCO-PMGD-2026.pdf
A15: ATENCION - DS 1/2026: incorporar BESS a un PMGD con precio estabilizado se considera "modificacion" y puede hacer PERDER el precio estabilizado | B15: Cuatrecasas | C15: https://www.cuatrecasas.com/es/latam/art/energia-infraestructura-pmgd-almacenamiento-alcances-reingreso-ds-1-2026
... A18: NO VERIFICADO - no publicar: "pipeline total sobre 36.000 MW"; "solo 7-10% del pipeline operativo"; "85% de las obras de transmision retrasadas" | B18: - | C18: Solo en fuentes secundarias e inconsistente con las cifras oficiales
