Workbook

Sheet Resultado_Anual
A1: Utilidades anuales — ventana 4 h, arbitraje a costo marginal (spot), sin PPA
A2: Carga 4 h en banda solar; venta 4 h en banda nocturna. Período base 2023–2026 (2022 se muestra como contexto; excluido del caso base por ser previo a la saturación solar, carga 45 > PPA 28). Volúmenes 6,57 / 5,46 GWh y PPA enlazados desde Supuestos.
A4: Año | B4: P. carga medio (USD/MWh) | C4: P. venta medio (USD/MWh) | D4: Spread (USD/MWh) | E4: Ingreso venta (USD/año) | F4: Costo carga spot (USD/año) | G4: Margen bruto (USD/año) | H4: Costo si PPA $28 (USD/año) | I4: Sobrecosto del PPA (USD/año)
A5: 2022 | B5: =AVERAGEIF(Despacho_Diario!$B$4:$B$1589,$A5,Despacho_Diario!$C$4:$C$1589) -> 45.026281 | C5: =AVERAGEIF(Despacho_Diario!$B$4:$B$1589,$A5,Despacho_Diario!$D$4:$D$1589) -> 184.824 | D5: =C5-B5 -> 139.79772 | E5: =Supuestos!$B$17*C5 -> 1009139 | F5: =Supuestos!$B$16*B5 -> 295822.66 | G5: =E5-F5 -> 713316.37 | H5: =Supuestos!$B$16*Supuestos!$B$10 -> 183960 | I5: =H5-F5 -> -111862.66
A6: 2023 | B6: =AVERAGEIF(Despacho_Diario!$B$4:$B$1589,$A6,Despacho_Diario!$C$4:$C$1589) -> 19.892925 | C6: =AVERAGEIF(Despacho_Diario!$B$4:$B$1589,$A6,Despacho_Diario!$D$4:$D$1589) -> 143.14328 | D6: =C6-B6 -> 123.25036 | E6: =Supuestos!$B$17*C6 -> 781562.31 | F6: =Supuestos!$B$16*B6 -> 130696.52 | G6: =E6-F6 -> 650865.8 | H6: =Supuestos!$B$16*Supuestos!$B$10 -> 183960 | I6: =H6-F6 -> 53263.485
A7: 2024 | B7: =AVERAGEIF(Despacho_Diario!$B$4:$B$1589,$A7,Despacho_Diario!$C$4:$C$1589) -> 8.0611234 | C7: =AVERAGEIF(Despacho_Diario!$B$4:$B$1589,$A7,Despacho_Diario!$D$4:$D$1589) -> 93.790125 | D7: =C7-B7 -> 85.729002 | E7: =Supuestos!$B$17*C7 -> 512094.08 | F7: =Supuestos!$B$16*B7 -> 52961.581 | G7: =E7-F7 -> 459132.5 | H7: =Supuestos!$B$16*Supuestos!$B$10 -> 183960 | I7: =H7-F7 -> 130998.42
A8: 2025 | B8: =AVERAGEIF(Despacho_Diario!$B$4:$B$1589,$A8,Despacho_Diario!$C$4:$C$1589) -> 24.007278 | C8: =AVERAGEIF(Despacho_Diario!$B$4:$B$1589,$A8,Despacho_Diario!$D$4:$D$1589) -> 113.03888 | D8: =C8-B8 -> 89.031607 | E8: =Supuestos!$B$17*C8 -> 617192.31 | F8: =Supuestos!$B$16*B8 -> 157727.81 | G8: =E8-F8 -> 459464.49 | H8: =Supuestos!$B$16*Supuestos!$B$10 -> 183960 | I8: =H8-F8 -> 26232.185
A9: 2026 | B9: =AVERAGEIF(Despacho_Diario!$B$4:$B$1589,$A9,Despacho_Diario!$C$4:$C$1589) -> 9.5974672 | C9: =AVERAGEIF(Despacho_Diario!$B$4:$B$1589,$A9,Despacho_Diario!$D$4:$D$1589) -> 84.992198 | D9: =C9-B9 -> 75.394731 | E9: =Supuestos!$B$17*C9 -> 464057.4 | F9: =Supuestos!$B$16*B9 -> 63055.36 | G9: =E9-F9 -> 401002.04 | H9: =Supuestos!$B$16*Supuestos!$B$10 -> 183960 | I9: =H9-F9 -> 120904.64
A10: Base 23–26 | B10: =AVERAGE(B6:B9) -> 15.389698 | C10: =AVERAGE(C6:C9) -> 108.74112 | D10: =C10-B10 -> 93.351424 | E10: =Supuestos!$B$17*C10 -> 593726.53 | F10: =Supuestos!$B$16*B10 -> 101110.32 | G10: =E10-F10 -> 492616.21 | H10: =Supuestos!$B$16*Supuestos!$B$10 -> 183960 | I10: =H10-F10 -> 82849.682
A12: Ventana de 4 h, carga 100% en banda solar. El "sobrecosto del PPA" es el mayor costo anual de comprar la energía
A13: de carga a US$28/MWh en vez de cargar a spot. Positivo = el PPA destruye margen. Solo 2022 (previo a la saturación solar) lo favorecía.
A14: El caso base promedia 2023–2026, el período más largo en que el costo de carga es inferior al PPA en todos los años. 2022 (carga 45 > PPA 28) se excluye por ser previo a la saturación fotovoltaica del nodo.

Sheet Supuestos
A1: Panimávida BESS 13,2 kV — Utilidades por arbitraje a costo marginal · ventana 4 h · base 2023–2026
A2: RHO Generación · a solicitud del FIP CEHTA Capital · Base: 38.064 horas reales del Coordinador Eléctrico Nacional (Real Definitivo) · 2022-01-01 a 2026-05-22
A4: Supuesto | B4: Valor | C4: Unidad | D4: Fuente / nota
A5: Potencia del sistema (BESS) | B5: 9 | C5: MW | D5: Ficha de proyecto
A6: Capacidad de almacenamiento | B6: 36 | C6: MWh | D6: Ficha de proyecto (duración 4 h)
A7: Energía de carga anual | B7: 6.57 | C7: GWh/año | D7: Plan de operación (~182 ciclos completos de 4 h al año)
A8: Energía de descarga anual (venta) | B8: 5.46 | C8: GWh/año | D8: Carga × eficiencia round-trip
A9: Eficiencia round-trip implícita | B9: =B8/B7 -> 0.83105023 | C9: — | D9: Descarga ÷ Carga; conservadora vs 88% nominal
A10: Precio PPA de compra (referencia) | B10: 28 | C10: USD/MWh | D10: Oferta PPA en evaluación
A11: Banda solar (carga) | B11: 09–17 h | C11: hora-reloj | D11: Carga = horas más baratas DENTRO de esta banda
A12: Banda nocturna (venta) | B12: 19–07 h | C12: hora-reloj | D12: Venta = horas más caras DENTRO de esta banda
A13: Horas seleccionadas por ciclo | B13: 4 | C13: h | D13: 4 más baratas (carga) / 4 más caras (venta)
A15: Volúmenes anuales en MWh (derivados):
A16: Carga (MWh/año) | B16: =B7*1000 -> 6570
A17: Descarga / venta (MWh/año) | B17: =B8*1000 -> 5460
A19: METODOLOGÍA
A20: El proyecto selecciona, cada día operado, las 4 horas de menor costo marginal de la banda solar (09–17 h) para cargar y las
A21: 4 de mayor costo de la banda nocturna (19–07 h) para vender. Los volúmenes anuales (6,57 GWh de carga y 5,46 GWh de venta)
A22: corresponden al plan de operación previsto, equivalente a ~182 ciclos completos de 4 h al año (uno cada ~2 días). El precio
A23: anual es el promedio de los valores diarios (Despacho_Diario → Resultado_Anual). Fórmulas vivas sobre los datos crudos.
A25: Convención de color: azul = supuesto editable · negro = fórmula · verde = vínculo entre hojas.

Sheet Datos_CMg
A1: Fecha | B1: Hora | C1: CMg_USD_MWh | D1: Año
A2: 2022-01-01 | B2: 0 | C2: 81.24 | D2: 2022
A3: 2022-01-01 | B3: 1 | C3: 93.02 | D3: 2022
A4: 2022-01-01 | B4: 2 | C4: 186.53 | D4: 2022
A5: 2022-01-01 | B5: 3 | C5: 151.14 | D5: 2022
A6: 2022-01-01 | B6: 4 | C6: 120.03 | D6: 2022
A7: 2022-01-01 | B7: 5 | C7: 120.03 | D7: 2022
A8: 2022-01-01 | B8: 6 | C8: 107.32 | D8: 2022
A9: 2022-01-01 | B9: 7 | C9: 53.54 | D9: 2022
A10: 2022-01-01 | B10: 8 | C10: 0 | D10: 2022
A11: 2022-01-01 | B11: 9 | C11: 0 | D11: 2022
A12: 2022-01-01 | B12: 10 | C12: 0 | D12: 2022
A13: 2022-01-01 | B13: 11 | C13: 0 | D13: 2022
... A38065: 2026-05-22 | B38065: 23 | C38065: 61.901578 | D38065: 2026

Sheet Despacho_Diario
A1: Despacho diario — ciclo 4 h: carga en banda solar (09–17 h) y venta en banda nocturna (19–07 h)
A2: Carga = promedio de las 4 horas más baratas de la banda solar. Venta = promedio de las 4 más caras de la banda nocturna (anochecer 19–23 + madrugada 00–07). Fórmulas vivas sobre Datos_CMg.
A3: Fecha | B3: Año | C3: P_carga (USD/MWh) | D3: P_venta (USD/MWh) | E3: Spread (USD/MWh) | F3: aux t1 | G3: aux t2 | H3: aux t3 | I3: aux t4 | J3: aux m1 | K3: aux m2 | L3: aux m3 | M3: aux m4
A4: 2022-01-01 | B4: =Datos_CMg!$D$2 -> 2022 | C4: =(SMALL(Datos_CMg!$C$11:$C$19,1)+SMALL(Datos_CMg!$C$11:$C$19,2)+SMALL(Datos_CMg!$C$11:$C$19,3)+SMALL(Datos_CMg!$C$11:$C$19,4))/4 -> 0 | D4: =(LARGE($F4:$M4,1)+LARGE($F4:$M4,2)+LARGE($F4:$M4,3)+LARGE($F4:$M4,4))/4 -> 144.4325 | E4: =D4-C4 -> 144.4325 | F4: =LARGE(Datos_CMg!$C$21:$C$25,1) -> 95.35 | G4: =LARGE(Datos_CMg!$C$21:$C$25,2) -> 81.43 | H4: =LARGE(Datos_CMg!$C$21:$C$25,3) -> 75.14 | I4: =LARGE(Datos_CMg!$C$21:$C$25,4) -> 73.52 | J4: =LARGE(Datos_CMg!$C$2:$C$9,1) -> 186.53 | K4: =LARGE(Datos_CMg!$C$2:$C$9,2) -> 151.14 | L4: =LARGE(Datos_CMg!$C$2:$C$9,3) -> 120.03 | M4: =LARGE(Datos_CMg!$C$2:$C$9,4) -> 120.03
A5: 2022-01-02 | B5: =Datos_CMg!$D$26 -> 2022 | C5: =(SMALL(Datos_CMg!$C$35:$C$43,1)+SMALL(Datos_CMg!$C$35:$C$43,2)+SMALL(Datos_CMg!$C$35:$C$43,3)+SMALL(Datos_CMg!$C$35:$C$43,4))/4 -> 0 | D5: =(LARGE($F5:$M5,1)+LARGE($F5:$M5,2)+LARGE($F5:$M5,3)+LARGE($F5:$M5,4))/4 -> 88.8975 | E5: =D5-C5 -> 88.8975 | F5: =LARGE(Datos_CMg!$C$45:$C$49,1) -> 88.35 | G5: =LARGE(Datos_CMg!$C$45:$C$49,2) -> 88.04 | H5: =LARGE(Datos_CMg!$C$45:$C$49,3) -> 77.4 | I5: =LARGE(Datos_CMg!$C$45:$C$49,4) -> 75.58 | J5: =LARGE(Datos_CMg!$C$26:$C$33,1) -> 101.8 | K5: =LARGE(Datos_CMg!$C$26:$C$33,2) -> 75.25 | L5: =LARGE(Datos_CMg!$C$26:$C$33,3) -> 74.43 | M5: =LARGE(Datos_CMg!$C$26:$C$33,4) -> 68.94
A6: 2022-01-03 | B6: =Datos_CMg!$D$50 -> 2022 | C6: =(SMALL(Datos_CMg!$C$59:$C$67,1)+SMALL(Datos_CMg!$C$59:$C$67,2)+SMALL(Datos_CMg!$C$59:$C$67,3)+SMALL(Datos_CMg!$C$59:$C$67,4))/4 -> 0 | D6: =(LARGE($F6:$M6,1)+LARGE($F6:$M6,2)+LARGE($F6:$M6,3)+LARGE($F6:$M6,4))/4 -> 158.9325 | E6: =D6-C6 -> 158.9325 | F6: =LARGE(Datos_CMg!$C$69:$C$73,1) -> 180.97 | G6: =LARGE(Datos_CMg!$C$69:$C$73,2) -> 173.76 | H6: =LARGE(Datos_CMg!$C$69:$C$73,3) -> 160.79 | I6: =LARGE(Datos_CMg!$C$69:$C$73,4) -> 107.99 | J6: =LARGE(Datos_CMg!$C$50:$C$57,1) -> 120.21 | K6: =LARGE(Datos_CMg!$C$50:$C$57,2) -> 114.91 | L6: =LARGE(Datos_CMg!$C$50:$C$57,3) -> 90.59 | M6: =LARGE(Datos_CMg!$C$50:$C$57,4) -> 90.59
A7: 2022-01-04 | B7: =Datos_CMg!$D$74 -> 2022 | C7: =(SMALL(Datos_CMg!$C$83:$C$91,1)+SMALL(Datos_CMg!$C$83:$C$91,2)+SMALL(Datos_CMg!$C$83:$C$91,3)+SMALL(Datos_CMg!$C$83:$C$91,4))/4 -> 45.7675 | D7: =(LARGE($F7:$M7,1)+LARGE($F7:$M7,2)+LARGE($F7:$M7,3)+LARGE($F7:$M7,4))/4 -> 131.71 | E7: =D7-C7 -> 85.9425 | F7: =LARGE(Datos_CMg!$C$93:$C$97,1) -> 102.88 | G7: =LARGE(Datos_CMg!$C$93:$C$97,2) -> 94.04 | H7: =LARGE(Datos_CMg!$C$93:$C$97,3) -> 83.74 | I7: =LARGE(Datos_CMg!$C$93:$C$97,4) -> 79.84 | J7: =LARGE(Datos_CMg!$C$74:$C$81,1) -> 134.17 | K7: =LARGE(Datos_CMg!$C$74:$C$81,2) -> 134.17 | L7: =LARGE(Datos_CMg!$C$74:$C$81,3) -> 134.17 | M7: =LARGE(Datos_CMg!$C$74:$C$81,4) -> 124.33
A8: 2022-01-05 | B8: =Datos_CMg!$D$98 -> 2022 | C8: =(SMALL(Datos_CMg!$C$107:$C$115,1)+SMALL(Datos_CMg!$C$107:$C$115,2)+SMALL(Datos_CMg!$C$107:$C$115,3)+SMALL(Datos_CMg!$C$107:$C$115,4))/4 -> 41.345 | D8: =(LARGE($F8:$M8,1)+LARGE($F8:$M8,2)+LARGE($F8:$M8,3)+LARGE($F8:$M8,4))/4 -> 122.98 | E8: =D8-C8 -> 81.635 | F8: =LARGE(Datos_CMg!$C$117:$C$121,1) -> 149.3 | G8: =LARGE(Datos_CMg!$C$117:$C$121,2) -> 128.26 | H8: =LARGE(Datos_CMg!$C$117:$C$121,3) -> 113.81 | I8: =LARGE(Datos_CMg!$C$117:$C$121,4) -> 100.55 | J8: =LARGE(Datos_CMg!$C$98:$C$105,1) -> 88.03 | K8: =LARGE(Datos_CMg!$C$98:$C$105,2) -> 75.01 | L8: =LARGE(Datos_CMg!$C$98:$C$105,3) -> 75.01 | M8: =LARGE(Datos_CMg!$C$98:$C$105,4) -> 75.01
A9: 2022-01-06 | B9: =Datos_CMg!$D$122 -> 2022 | C9: =(SMALL(Datos_CMg!$C$131:$C$139,1)+SMALL(Datos_CMg!$C$131:$C$139,2)+SMALL(Datos_CMg!$C$131:$C$139,3)+SMALL(Datos_CMg!$C$131:$C$139,4))/4 -> 57.4525 | D9: =(LARGE($F9:$M9,1)+LARGE($F9:$M9,2)+LARGE($F9:$M9,3)+LARGE($F9:$M9,4))/4 -> 106.965 | E9: =D9-C9 -> 49.5125 | F9: =LARGE(Datos_CMg!$C$141:$C$145,1) -> 111.08 | G9: =LARGE(Datos_CMg!$C$141:$C$145,2) -> 111.08 | H9: =LARGE(Datos_CMg!$C$141:$C$145,3) -> 109.21 | I9: =LARGE(Datos_CMg!$C$141:$C$145,4) -> 96.49 | J9: =LARGE(Datos_CMg!$C$122:$C$129,1) -> 87.1 | K9: =LARGE(Datos_CMg!$C$122:$C$129,2) -> 83.51 | L9: =LARGE(Datos_CMg!$C$122:$C$129,3) -> 81.8 | M9: =LARGE(Datos_CMg!$C$122:$C$129,4) -> 81.41
A10: 2022-01-07 | B10: =Datos_CMg!$D$146 -> 2022 | C10: =(SMALL(Datos_CMg!$C$155:$C$163,1)+SMALL(Datos_CMg!$C$155:$C$163,2)+SMALL(Datos_CMg!$C$155:$C$163,3)+SMALL(Datos_CMg!$C$155:$C$163,4))/4 -> 53.0125 | D10: =(LARGE($F10:$M10,1)+LARGE($F10:$M10,2)+LARGE($F10:$M10,3)+LARGE($F10:$M10,4))/4 -> 207.075 | E10: =D10-C10 -> 154.0625 | F10: =LARGE(Datos_CMg!$C$165:$C$169,1) -> 216.76 | G10: =LARGE(Datos_CMg!$C$165:$C$169,2) -> 214.06 | H10: =LARGE(Datos_CMg!$C$165:$C$169,3) -> 183.5 | I10: =LARGE(Datos_CMg!$C$165:$C$169,4) -> 130.48 | J10: =LARGE(Datos_CMg!$C$146:$C$153,1) -> 198.74 | K10: =LARGE(Datos_CMg!$C$146:$C$153,2) -> 198.74 | L10: =LARGE(Datos_CMg!$C$146:$C$153,3) -> 194.27 | M10: =LARGE(Datos_CMg!$C$146:$C$153,4) -> 190.14
A11: 2022-01-08 | B11: =Datos_CMg!$D$170 -> 2022 | C11: =(SMALL(Datos_CMg!$C$179:$C$187,1)+SMALL(Datos_CMg!$C$179:$C$187,2)+SMALL(Datos_CMg!$C$179:$C$187,3)+SMALL(Datos_CMg!$C$179:$C$187,4))/4 -> 0 | D11: =(LARGE($F11:$M11,1)+LARGE($F11:$M11,2)+LARGE($F11:$M11,3)+LARGE($F11:$M11,4))/4 -> 222.2175 | E11: =D11-C11 -> 222.2175 | F11: =LARGE(Datos_CMg!$C$189:$C$193,1) -> 225.74 | G11: =LARGE(Datos_CMg!$C$189:$C$193,2) -> 225.32 | H11: =LARGE(Datos_CMg!$C$189:$C$193,3) -> 221.92 | I11: =LARGE(Datos_CMg!$C$189:$C$193,4) -> 193.1 | J11: =LARGE(Datos_CMg!$C$170:$C$177,1) -> 215.89 | K11: =LARGE(Datos_CMg!$C$170:$C$177,2) -> 212.27 | L11: =LARGE(Datos_CMg!$C$170:$C$177,3) -> 210.72 | M11: =LARGE(Datos_CMg!$C$170:$C$177,4) -> 209.65
A12: 2022-01-09 | B12: =Datos_CMg!$D$194 -> 2022 | C12: =(SMALL(Datos_CMg!$C$203:$C$211,1)+SMALL(Datos_CMg!$C$203:$C$211,2)+SMALL(Datos_CMg!$C$203:$C$211,3)+SMALL(Datos_CMg!$C$203:$C$211,4))/4 -> 0 | D12: =(LARGE($F12:$M12,1)+LARGE($F12:$M12,2)+LARGE($F12:$M12,3)+LARGE($F12:$M12,4))/4 -> 214.405 | E12: =D12-C12 -> 214.405 | F12: =LARGE(Datos_CMg!$C$213:$C$217,1) -> 217.61 | G12: =LARGE(Datos_CMg!$C$213:$C$217,2) -> 217.61 | H12: =LARGE(Datos_CMg!$C$213:$C$217,3) -> 203.17 | I12: =LARGE(Datos_CMg!$C$213:$C$217,4) -> 202.94 | J12: =LARGE(Datos_CMg!$C$194:$C$201,1) -> 211.2 | K12: =LARGE(Datos_CMg!$C$194:$C$201,2) -> 211.2 | L12: =LARGE(Datos_CMg!$C$194:$C$201,3) -> 206.6 | M12: =LARGE(Datos_CMg!$C$194:$C$201,4) -> 155.94
A13: 2022-01-10 | B13: =Datos_CMg!$D$218 -> 2022 | C13: =(SMALL(Datos_CMg!$C$227:$C$235,1)+SMALL(Datos_CMg!$C$227:$C$235,2)+SMALL(Datos_CMg!$C$227:$C$235,3)+SMALL(Datos_CMg!$C$227:$C$235,4))/4 -> 0 | D13: =(LARGE($F13:$M13,1)+LARGE($F13:$M13,2)+LARGE($F13:$M13,3)+LARGE($F13:$M13,4))/4 -> 179.6075 | E13: =D13-C13 -> 179.6075 | F13: =LARGE(Datos_CMg!$C$237:$C$241,1) -> 186.25 | G13: =LARGE(Datos_CMg!$C$237:$C$241,2) -> 186.25 | H13: =LARGE(Datos_CMg!$C$237:$C$241,3) -> 183.29 | I13: =LARGE(Datos_CMg!$C$237:$C$241,4) -> 155.79 | J13: =LARGE(Datos_CMg!$C$218:$C$225,1) -> 162.64 | K13: =LARGE(Datos_CMg!$C$218:$C$225,2) -> 159.61 | L13: =LARGE(Datos_CMg!$C$218:$C$225,3) -> 159.61 | M13: =LARGE(Datos_CMg!$C$218:$C$225,4) -> 159.61
A14: 2022-01-11 | B14: =Datos_CMg!$D$242 -> 2022 | C14: =(SMALL(Datos_CMg!$C$251:$C$259,1)+SMALL(Datos_CMg!$C$251:$C$259,2)+SMALL(Datos_CMg!$C$251:$C$259,3)+SMALL(Datos_CMg!$C$251:$C$259,4))/4 -> 0 | D14: =(LARGE($F14:$M14,1)+LARGE($F14:$M14,2)+LARGE($F14:$M14,3)+LARGE($F14:$M14,4))/4 -> 193.515 | E14: =D14-C14 -> 193.515 | F14: =LARGE(Datos_CMg!$C$261:$C$265,1) -> 207.49 | G14: =LARGE(Datos_CMg!$C$261:$C$265,2) -> 207.49 | H14: =LARGE(Datos_CMg!$C$261:$C$265,3) -> 173.67 | I14: =LARGE(Datos_CMg!$C$261:$C$265,4) -> 156.65 | J14: =LARGE(Datos_CMg!$C$242:$C$249,1) -> 179.54 | K14: =LARGE(Datos_CMg!$C$242:$C$249,2) -> 179.54 | L14: =LARGE(Datos_CMg!$C$242:$C$249,3) -> 114.23 | M14: =LARGE(Datos_CMg!$C$242:$C$249,4) -> 101.77
A15: 2022-01-12 | B15: =Datos_CMg!$D$266 -> 2022 | C15: =(SMALL(Datos_CMg!$C$275:$C$283,1)+SMALL(Datos_CMg!$C$275:$C$283,2)+SMALL(Datos_CMg!$C$275:$C$283,3)+SMALL(Datos_CMg!$C$275:$C$283,4))/4 -> 0 | D15: =(LARGE($F15:$M15,1)+LARGE($F15:$M15,2)+LARGE($F15:$M15,3)+LARGE($F15:$M15,4))/4 -> 134.945 | E15: =D15-C15 -> 134.945 | F15: =LARGE(Datos_CMg!$C$285:$C$289,1) -> 135.4 | G15: =LARGE(Datos_CMg!$C$285:$C$289,2) -> 135.4 | H15: =LARGE(Datos_CMg!$C$285:$C$289,3) -> 132.05 | I15: =LARGE(Datos_CMg!$C$285:$C$289,4) -> 113.09 | J15: =LARGE(Datos_CMg!$C$266:$C$273,1) -> 136.93 | K15: =LARGE(Datos_CMg!$C$266:$C$273,2) -> 127.72 | L15: =LARGE(Datos_CMg!$C$266:$C$273,3) -> 117.79 | M15: =LARGE(Datos_CMg!$C$266:$C$273,4) -> 98.99
A16: 2022-01-13 | B16: =Datos_CMg!$D$290 -> 2022 | C16: =(SMALL(Datos_CMg!$C$299:$C$307,1)+SMALL(Datos_CMg!$C$299:$C$307,2)+SMALL(Datos_CMg!$C$299:$C$307,3)+SMALL(Datos_CMg!$C$299:$C$307,4))/4 -> 0 | D16: =(LARGE($F16:$M16,1)+LARGE($F16:$M16,2)+LARGE($F16:$M16,3)+LARGE($F16:$M16,4))/4 -> 99.2875 | E16: =D16-C16 -> 99.2875 | F16: =LARGE(Datos_CMg!$C$309:$C$313,1) -> 100.12 | G16: =LARGE(Datos_CMg!$C$309:$C$313,2) -> 88.55 | H16: =LARGE(Datos_CMg!$C$309:$C$313,3) -> 81.47 | I16: =LARGE(Datos_CMg!$C$309:$C$313,4) -> 80.35 | J16: =LARGE(Datos_CMg!$C$290:$C$297,1) -> 101.2 | K16: =LARGE(Datos_CMg!$C$290:$C$297,2) -> 98.96 | L16: =LARGE(Datos_CMg!$C$290:$C$297,3) -> 96.87 | M16: =LARGE(Datos_CMg!$C$290:$C$297,4) -> 86.36
A17: 2022-01-14 | B17: =Datos_CMg!$D$314 -> 2022 | C17: =(SMALL(Datos_CMg!$C$323:$C$331,1)+SMALL(Datos_CMg!$C$323:$C$331,2)+SMALL(Datos_CMg!$C$323:$C$331,3)+SMALL(Datos_CMg!$C$323:$C$331,4))/4 -> 0 | D17: =(LARGE($F17:$M17,1)+LARGE($F17:$M17,2)+LARGE($F17:$M17,3)+LARGE($F17:$M17,4))/4 -> 87.62 | E17: =D17-C17 -> 87.62 | F17: =LARGE(Datos_CMg!$C$333:$C$337,1) -> 88.66 | G17: =LARGE(Datos_CMg!$C$333:$C$337,2) -> 87.67 | H17: =LARGE(Datos_CMg!$C$333:$C$337,3) -> 87.28 | I17: =LARGE(Datos_CMg!$C$333:$C$337,4) -> 86.87 | J17: =LARGE(Datos_CMg!$C$314:$C$321,1) -> 81.22 | K17: =LARGE(Datos_CMg!$C$314:$C$321,2) -> 81.22 | L17: =LARGE(Datos_CMg!$C$314:$C$321,3) -> 77.42 | M17: =LARGE(Datos_CMg!$C$314:$C$321,4) -> 75.44
A18: 2022-01-15 | B18: =Datos_CMg!$D$338 -> 2022 | C18: =(SMALL(Datos_CMg!$C$347:$C$355,1)+SMALL(Datos_CMg!$C$347:$C$355,2)+SMALL(Datos_CMg!$C$347:$C$355,3)+SMALL(Datos_CMg!$C$347:$C$355,4))/4 -> 0 | D18: =(LARGE($F18:$M18,1)+LARGE($F18:$M18,2)+LARGE($F18:$M18,3)+LARGE($F18:$M18,4))/4 -> 80.6725 | E18: =D18-C18 -> 80.6725 | F18: =LARGE(Datos_CMg!$C$357:$C$361,1) -> 80.74 | G18: =LARGE(Datos_CMg!$C$357:$C$361,2) -> 78.5 | H18: =LARGE(Datos_CMg!$C$357:$C$361,3) -> 74.07 | I18: =LARGE(Datos_CMg!$C$357:$C$361,4) -> 71.15 | J18: =LARGE(Datos_CMg!$C$338:$C$345,1) -> 80.65 | K18: =LARGE(Datos_CMg!$C$338:$C$345,2) -> 80.65 | L18: =LARGE(Datos_CMg!$C$338:$C$345,3) -> 80.65 | M18: =LARGE(Datos_CMg!$C$338:$C$345,4) -> 79.23
A19: 2022-01-16 | B19: =Datos_CMg!$D$362 -> 2022 | C19: =(SMALL(Datos_CMg!$C$371:$C$379,1)+SMALL(Datos_CMg!$C$371:$C$379,2)+SMALL(Datos_CMg!$C$371:$C$379,3)+SMALL(Datos_CMg!$C$371:$C$379,4))/4 -> 0 | D19: =(LARGE($F19:$M19,1)+LARGE($F19:$M19,2)+LARGE($F19:$M19,3)+LARGE($F19:$M19,4))/4 -> 81.975 | E19: =D19-C19 -> 81.975 | F19: =LARGE(Datos_CMg!$C$381:$C$385,1) -> 83.62 | G19: =LARGE(Datos_CMg!$C$381:$C$385,2) -> 81.96 | H19: =LARGE(Datos_CMg!$C$381:$C$385,3) -> 77.6 | I19: =LARGE(Datos_CMg!$C$381:$C$385,4) -> 73.25 | J19: =LARGE(Datos_CMg!$C$362:$C$369,1) -> 81.16 | K19: =LARGE(Datos_CMg!$C$362:$C$369,2) -> 81.16 | L19: =LARGE(Datos_CMg!$C$362:$C$369,3) -> 81.16 | M19: =LARGE(Datos_CMg!$C$362:$C$369,4) -> 81.11
A20: 2022-01-17 | B20: =Datos_CMg!$D$386 -> 2022 | C20: =(SMALL(Datos_CMg!$C$395:$C$403,1)+SMALL(Datos_CMg!$C$395:$C$403,2)+SMALL(Datos_CMg!$C$395:$C$403,3)+SMALL(Datos_CMg!$C$395:$C$403,4))/4 -> 0.5375 | D20: =(LARGE($F20:$M20,1)+LARGE($F20:$M20,2)+LARGE($F20:$M20,3)+LARGE($F20:$M20,4))/4 -> 84.2075 | E20: =D20-C20 -> 83.67 | F20: =LARGE(Datos_CMg!$C$405:$C$409,1) -> 88.32 | G20: =LARGE(Datos_CMg!$C$405:$C$409,2) -> 85.83 | H20: =LARGE(Datos_CMg!$C$405:$C$409,3) -> 81.42 | I20: =LARGE(Datos_CMg!$C$405:$C$409,4) -> 81.26 | J20: =LARGE(Datos_CMg!$C$386:$C$393,1) -> 80.38 | K20: =LARGE(Datos_CMg!$C$386:$C$393,2) -> 80.38 | L20: =LARGE(Datos_CMg!$C$386:$C$393,3) -> 80.38 | M20: =LARGE(Datos_CMg!$C$386:$C$393,4) -> 78.98
A21: 2022-01-18 | B21: =Datos_CMg!$D$410 -> 2022 | C21: =(SMALL(Datos_CMg!$C$419:$C$427,1)+SMALL(Datos_CMg!$C$419:$C$427,2)+SMALL(Datos_CMg!$C$419:$C$427,3)+SMALL(Datos_CMg!$C$419:$C$427,4))/4 -> 0 | D21: =(LARGE($F21:$M21,1)+LARGE($F21:$M21,2)+LARGE($F21:$M21,3)+LARGE($F21:$M21,4))/4 -> 84.13 | E21: =D21-C21 -> 84.13 | F21: =LARGE(Datos_CMg!$C$429:$C$433,1) -> 89.64 | G21: =LARGE(Datos_CMg!$C$429:$C$433,2) -> 88.26 | H21: =LARGE(Datos_CMg!$C$429:$C$433,3) -> 76.84 | I21: =LARGE(Datos_CMg!$C$429:$C$433,4) -> 72.71 | J21: =LARGE(Datos_CMg!$C$410:$C$417,1) -> 80.41 | K21: =LARGE(Datos_CMg!$C$410:$C$417,2) -> 78.21 | L21: =LARGE(Datos_CMg!$C$410:$C$417,3) -> 78.21 | M21: =LARGE(Datos_CMg!$C$410:$C$417,4) -> 77.31
A22: 2022-01-19 | B22: =Datos_CMg!$D$434 -> 2022 | C22: =(SMALL(Datos_CMg!$C$443:$C$451,1)+SMALL(Datos_CMg!$C$443:$C$451,2)+SMALL(Datos_CMg!$C$443:$C$451,3)+SMALL(Datos_CMg!$C$443:$C$451,4))/4 -> 0 | D22: =(LARGE($F22:$M22,1)+LARGE($F22:$M22,2)+LARGE($F22:$M22,3)+LARGE($F22:$M22,4))/4 -> 80.8 | E22: =D22-C22 -> 80.8 | F22: =LARGE(Datos_CMg!$C$453:$C$457,1) -> 82.74 | G22: =LARGE(Datos_CMg!$C$453:$C$457,2) -> 75.43 | H22: =LARGE(Datos_CMg!$C$453:$C$457,3) -> 72.56 | I22: =LARGE(Datos_CMg!$C$453:$C$457,4) -> 35.85 | J22: =LARGE(Datos_CMg!$C$434:$C$441,1) -> 80.59 | K22: =LARGE(Datos_CMg!$C$434:$C$441,2) -> 80.59 | L22: =LARGE(Datos_CMg!$C$434:$C$441,3) -> 79.28 | M22: =LARGE(Datos_CMg!$C$434:$C$441,4) -> 77.64
A23: 2022-01-20 | B23: =Datos_CMg!$D$458 -> 2022 | C23: =(SMALL(Datos_CMg!$C$467:$C$475,1)+SMALL(Datos_CMg!$C$467:$C$475,2)+SMALL(Datos_CMg!$C$467:$C$475,3)+SMALL(Datos_CMg!$C$467:$C$475,4))/4 -> 0 | D23: =(LARGE($F23:$M23,1)+LARGE($F23:$M23,2)+LARGE($F23:$M23,3)+LARGE($F23:$M23,4))/4 -> 82.77 | E23: =D23-C23 -> 82.77 | F23: =LARGE(Datos_CMg!$C$477:$C$481,1) -> 88.5 | G23: =LARGE(Datos_CMg!$C$477:$C$481,2) -> 87.88 | H23: =LARGE(Datos_CMg!$C$477:$C$481,3) -> 79.52 | I23: =LARGE(Datos_CMg!$C$477:$C$481,4) -> 75.18 | J23: =LARGE(Datos_CMg!$C$458:$C$465,1) -> 73.61 | K23: =LARGE(Datos_CMg!$C$458:$C$465,2) -> 73.43 | L23: =LARGE(Datos_CMg!$C$458:$C$465,3) -> 72.56 | M23: =LARGE(Datos_CMg!$C$458:$C$465,4) -> 70.94
A24: 2022-01-21 | B24: =Datos_CMg!$D$482 -> 2022 | C24: =(SMALL(Datos_CMg!$C$491:$C$499,1)+SMALL(Datos_CMg!$C$491:$C$499,2)+SMALL(Datos_CMg!$C$491:$C$499,3)+SMALL(Datos_CMg!$C$491:$C$499,4))/4 -> 0 | D24: =(LARGE($F24:$M24,1)+LARGE($F24:$M24,2)+LARGE($F24:$M24,3)+LARGE($F24:$M24,4))/4 -> 88.4175 | E24: =D24-C24 -> 88.4175 | F24: =LARGE(Datos_CMg!$C$501:$C$505,1) -> 90.64 | G24: =LARGE(Datos_CMg!$C$501:$C$505,2) -> 89.93 | H24: =LARGE(Datos_CMg!$C$501:$C$505,3) -> 86.55 | I24: =LARGE(Datos_CMg!$C$501:$C$505,4) -> 86.55 | J24: =LARGE(Datos_CMg!$C$482:$C$489,1) -> 74.65 | K24: =LARGE(Datos_CMg!$C$482:$C$489,2) -> 74.6 | L24: =LARGE(Datos_CMg!$C$482:$C$489,3) -> 73.77 | M24: =LARGE(Datos_CMg!$C$482:$C$489,4) -> 73.74
A25: 2022-01-22 | B25: =Datos_CMg!$D$506 -> 2022 | C25: =(SMALL(Datos_CMg!$C$515:$C$523,1)+SMALL(Datos_CMg!$C$515:$C$523,2)+SMALL(Datos_CMg!$C$515:$C$523,3)+SMALL(Datos_CMg!$C$515:$C$523,4))/4 -> 0 | D25: =(LARGE($F25:$M25,1)+LARGE($F25:$M25,2)+LARGE($F25:$M25,3)+LARGE($F25:$M25,4))/4 -> 82.715 | E25: =D25-C25 -> 82.715 | F25: =LARGE(Datos_CMg!$C$525:$C$529,1) -> 83.6 | G25: =LARGE(Datos_CMg!$C$525:$C$529,2) -> 80.19 | H25: =LARGE(Datos_CMg!$C$525:$C$529,3) -> 73.7 | I25: =LARGE(Datos_CMg!$C$525:$C$529,4) -> 73.7 | J25: =LARGE(Datos_CMg!$C$506:$C$513,1) -> 82.42 | K25: =LARGE(Datos_CMg!$C$506:$C$513,2) -> 82.42 | L25: =LARGE(Datos_CMg!$C$506:$C$513,3) -> 82.42 | M25: =LARGE(Datos_CMg!$C$506:$C$513,4) -> 78.5
A26: 2022-01-23 | B26: =Datos_CMg!$D$530 -> 2022 | C26: =(SMALL(Datos_CMg!$C$539:$C$547,1)+SMALL(Datos_CMg!$C$539:$C$547,2)+SMALL(Datos_CMg!$C$539:$C$547,3)+SMALL(Datos_CMg!$C$539:$C$547,4))/4 -> 0 | D26: =(LARGE($F26:$M26,1)+LARGE($F26:$M26,2)+LARGE($F26:$M26,3)+LARGE($F26:$M26,4))/4 -> 86.755 | E26: =D26-C26 -> 86.755 | F26: =LARGE(Datos_CMg!$C$549:$C$553,1) -> 94.06 | G26: =LARGE(Datos_CMg!$C$549:$C$553,2) -> 84.32 | H26: =LARGE(Datos_CMg!$C$549:$C$553,3) -> 84.32 | I26: =LARGE(Datos_CMg!$C$549:$C$553,4) -> 84.32 | J26: =LARGE(Datos_CMg!$C$530:$C$537,1) -> 75.08 | K26: =LARGE(Datos_CMg!$C$530:$C$537,2) -> 72.21 | L26: =LARGE(Datos_CMg!$C$530:$C$537,3) -> 72.04 | M26: =LARGE(Datos_CMg!$C$530:$C$537,4) -> 71.9
A27: 2022-01-24 | B27: =Datos_CMg!$D$554 -> 2022 | C27: =(SMALL(Datos_CMg!$C$563:$C$571,1)+SMALL(Datos_CMg!$C$563:$C$571,2)+SMALL(Datos_CMg!$C$563:$C$571,3)+SMALL(Datos_CMg!$C$563:$C$571,4))/4 -> 0 | D27: =(LARGE($F27:$M27,1)+LARGE($F27:$M27,2)+LARGE($F27:$M27,3)+LARGE($F27:$M27,4))/4 -> 149.7675 | E27: =D27-C27 -> 149.7675 | F27: =LARGE(Datos_CMg!$C$573:$C$577,1) -> 176.34 | G27: =LARGE(Datos_CMg!$C$573:$C$577,2) -> 176.34 | H27: =LARGE(Datos_CMg!$C$573:$C$577,3) -> 148.68 | I27: =LARGE(Datos_CMg!$C$573:$C$577,4) -> 97.71 | J27: =LARGE(Datos_CMg!$C$554:$C$561,1) -> 84.97 | K27: =LARGE(Datos_CMg!$C$554:$C$561,2) -> 84.92 | L27: =LARGE(Datos_CMg!$C$554:$C$561,3) -> 84.47 | M27: =LARGE(Datos_CMg!$C$554:$C$561,4) -> 83.98
A28: 2022-01-25 | B28: =Datos_CMg!$D$578 -> 2022 | C28: =(SMALL(Datos_CMg!$C$587:$C$595,1)+SMALL(Datos_CMg!$C$587:$C$595,2)+SMALL(Datos_CMg!$C$587:$C$595,3)+SMALL(Datos_CMg!$C$587:$C$595,4))/4 -> 26.2125 | D28: =(LARGE($F28:$M28,1)+LARGE($F28:$M28,2)+LARGE($F28:$M28,3)+LARGE($F28:$M28,4))/4 -> 156.0875 | E28: =D28-C28 -> 129.875 | F28: =LARGE(Datos_CMg!$C$597:$C$601,1) -> 168.71 | G28: =LARGE(Datos_CMg!$C$597:$C$601,2) -> 161.5 | H28: =LARGE(Datos_CMg!$C$597:$C$601,3) -> 156.92 | I28: =LARGE(Datos_CMg!$C$597:$C$601,4) -> 137.22 | J28: =LARGE(Datos_CMg!$C$578:$C$585,1) -> 99.58 | K28: =LARGE(Datos_CMg!$C$578:$C$585,2) -> 92.59 | L28: =LARGE(Datos_CMg!$C$578:$C$585,3) -> 88.38 | M28: =LARGE(Datos_CMg!$C$578:$C$585,4) -> 87.4
A29: 2022-01-26 | B29: =Datos_CMg!$D$602 -> 2022 | C29: =(SMALL(Datos_CMg!$C$611:$C$619,1)+SMALL(Datos_CMg!$C$611:$C$619,2)+SMALL(Datos_CMg!$C$611:$C$619,3)+SMALL(Datos_CMg!$C$611:$C$619,4))/4 -> 0 | D29: =(LARGE($F29:$M29,1)+LARGE($F29:$M29,2)+LARGE($F29:$M29,3)+LARGE($F29:$M29,4))/4 -> 207.525 | E29: =D29-C29 -> 207.525 | F29: =LARGE(Datos_CMg!$C$621:$C$625,1) -> 175.29 | G29: =LARGE(Datos_CMg!$C$621:$C$625,2) -> 171.08 | H29: =LARGE(Datos_CMg!$C$621:$C$625,3) -> 159.33 | I29: =LARGE(Datos_CMg!$C$621:$C$625,4) -> 152.3 | J29: =LARGE(Datos_CMg!$C$602:$C$609,1) -> 210.18 | K29: =LARGE(Datos_CMg!$C$602:$C$609,2) -> 210.18 | L29: =LARGE(Datos_CMg!$C$602:$C$609,3) -> 210.18 | M29: =LARGE(Datos_CMg!$C$602:$C$609,4) -> 199.56
A30: 2022-01-27 | B30: =Datos_CMg!$D$626 -> 2022 | C30: =(SMALL(Datos_CMg!$C$635:$C$643,1)+SMALL(Datos_CMg!$C$635:$C$643,2)+SMALL(Datos_CMg!$C$635:$C$643,3)+SMALL(Datos_CMg!$C$635:$C$643,4))/4 -> 63.3975 | D30: =(LARGE($F30:$M30,1)+LARGE($F30:$M30,2)+LARGE($F30:$M30,3)+LARGE($F30:$M30,4))/4 -> 214.275 | E30: =D30-C30 -> 150.8775 | F30: =LARGE(Datos_CMg!$C$645:$C$649,1) -> 114.55 | G30: =LARGE(Datos_CMg!$C$645:$C$649,2) -> 114.55 | H30: =LARGE(Datos_CMg!$C$645:$C$649,3) -> 114.55 | I30: =LARGE(Datos_CMg!$C$645:$C$649,4) -> 114.55 | J30: =LARGE(Datos_CMg!$C$626:$C$633,1) -> 229.47 | K30: =LARGE(Datos_CMg!$C$626:$C$633,2) -> 220.09 | L30: =LARGE(Datos_CMg!$C$626:$C$633,3) -> 211.09 | M30: =LARGE(Datos_CMg!$C$626:$C$633,4) -> 196.45
A31: 2022-01-28 | B31: =Datos_CMg!$D$650 -> 2022 | C31: =(SMALL(Datos_CMg!$C$659:$C$667,1)+SMALL(Datos_CMg!$C$659:$C$667,2)+SMALL(Datos_CMg!$C$659:$C$667,3)+SMALL(Datos_CMg!$C$659:$C$667,4))/4 -> 42.2425 | D31: =(LARGE($F31:$M31,1)+LARGE($F31:$M31,2)+LARGE($F31:$M31,3)+LARGE($F31:$M31,4))/4 -> 124.29 | E31: =D31-C31 -> 82.0475 | F31: =LARGE(Datos_CMg!$C$669:$C$673,1) -> 97.22 | G31: =LARGE(Datos_CMg!$C$669:$C$673,2) -> 85.65 | H31: =LARGE(Datos_CMg!$C$669:$C$673,3) -> 85.65 | I31: =LARGE(Datos_CMg!$C$669:$C$673,4) -> 85.65 | J31: =LARGE(Datos_CMg!$C$650:$C$657,1) -> 146.45 | K31: =LARGE(Datos_CMg!$C$650:$C$657,2) -> 138.11 | L31: =LARGE(Datos_CMg!$C$650:$C$657,3) -> 106.3 | M31: =LARGE(Datos_CMg!$C$650:$C$657,4) -> 106.3
A32: 2022-01-29 | B32: =Datos_CMg!$D$674 -> 2022 | C32: =(SMALL(Datos_CMg!$C$683:$C$691,1)+SMALL(Datos_CMg!$C$683:$C$691,2)+SMALL(Datos_CMg!$C$683:$C$691,3)+SMALL(Datos_CMg!$C$683:$C$691,4))/4 -> 0 | D32: =(LARGE($F32:$M32,1)+LARGE($F32:$M32,2)+LARGE($F32:$M32,3)+LARGE($F32:$M32,4))/4 -> 108.37 | E32: =D32-C32 -> 108.37 | F32: =LARGE(Datos_CMg!$C$693:$C$697,1) -> 115.98 | G32: =LARGE(Datos_CMg!$C$693:$C$697,2) -> 115.38 | H32: =LARGE(Datos_CMg!$C$693:$C$697,3) -> 112.62 | I32: =LARGE(Datos_CMg!$C$693:$C$697,4) -> 85.7 | J32: =LARGE(Datos_CMg!$C$674:$C$681,1) -> 89.5 | K32: =LARGE(Datos_CMg!$C$674:$C$681,2) -> 81.85 | L32: =LARGE(Datos_CMg!$C$674:$C$681,3) -> 81.85 | M32: =LARGE(Datos_CMg!$C$674:$C$681,4) -> 81.85
A33: 2022-01-30 | B33: =Datos_CMg!$D$698 -> 2022 | C33: =(SMALL(Datos_CMg!$C$707:$C$715,1)+SMALL(Datos_CMg!$C$707:$C$715,2)+SMALL(Datos_CMg!$C$707:$C$715,3)+SMALL(Datos_CMg!$C$707:$C$715,4))/4 -> 0 | D33: =(LARGE($F33:$M33,1)+LARGE($F33:$M33,2)+LARGE($F33:$M33,3)+LARGE($F33:$M33,4))/4 -> 79.4675 | E33: =D33-C33 -> 79.4675 | F33: =LARGE(Datos_CMg!$C$717:$C$721,1) -> 82.26 | G33: =LARGE(Datos_CMg!$C$717:$C$721,2) -> 80.53 | H33: =LARGE(Datos_CMg!$C$717:$C$721,3) -> 78.82 | I33: =LARGE(Datos_CMg!$C$717:$C$721,4) -> 75.74 | J33: =LARGE(Datos_CMg!$C$698:$C$705,1) -> 76.26 | K33: =LARGE(Datos_CMg!$C$698:$C$705,2) -> 75.03 | L33: =LARGE(Datos_CMg!$C$698:$C$705,3) -> 74.99 | M33: =LARGE(Datos_CMg!$C$698:$C$705,4) -> 74.78
A34: 2022-01-31 | B34: =Datos_CMg!$D$722 -> 2022 | C34: =(SMALL(Datos_CMg!$C$731:$C$739,1)+SMALL(Datos_CMg!$C$731:$C$739,2)+SMALL(Datos_CMg!$C$731:$C$739,3)+SMALL(Datos_CMg!$C$731:$C$739,4))/4 -> 38.73 | D34: =(LARGE($F34:$M34,1)+LARGE($F34:$M34,2)+LARGE($F34:$M34,3)+LARGE($F34:$M34,4))/4 -> 84.78 | E34: =D34-C34 -> 46.05 | F34: =LARGE(Datos_CMg!$C$741:$C$745,1) -> 85.12 | G34: =LARGE(Datos_CMg!$C$741:$C$745,2) -> 85.1 | H34: =LARGE(Datos_CMg!$C$741:$C$745,3) -> 84.48 | I34: =LARGE(Datos_CMg!$C$741:$C$745,4) -> 84.42 | J34: =LARGE(Datos_CMg!$C$722:$C$729,1) -> 82.63 | K34: =LARGE(Datos_CMg!$C$722:$C$729,2) -> 79.39 | L34: =LARGE(Datos_CMg!$C$722:$C$729,3) -> 72.61 | M34: =LARGE(Datos_CMg!$C$722:$C$729,4) -> 70.73
A35: 2022-02-01 | B35: =Datos_CMg!$D$746 -> 2022 | C35: =(SMALL(Datos_CMg!$C$755:$C$763,1)+SMALL(Datos_CMg!$C$755:$C$763,2)+SMALL(Datos_CMg!$C$755:$C$763,3)+SMALL(Datos_CMg!$C$755:$C$763,4))/4 -> 54.9825 | D35: =(LARGE($F35:$M35,1)+LARGE($F35:$M35,2)+LARGE($F35:$M35,3)+LARGE($F35:$M35,4))/4 -> 158.3525 | E35: =D35-C35 -> 103.37 | F35: =LARGE(Datos_CMg!$C$765:$C$769,1) -> 185.74 | G35: =LARGE(Datos_CMg!$C$765:$C$769,2) -> 185.74 | H35: =LARGE(Datos_CMg!$C$765:$C$769,3) -> 155.56 | I35: =LARGE(Datos_CMg!$C$765:$C$769,4) -> 106.37 | J35: =LARGE(Datos_CMg!$C$746:$C$753,1) -> 83.77 | K35: =LARGE(Datos_CMg!$C$746:$C$753,2) -> 83.77 | L35: =LARGE(Datos_CMg!$C$746:$C$753,3) -> 83.77 | M35: =LARGE(Datos_CMg!$C$746:$C$753,4) -> 83.39
A36: 2022-02-02 | B36: =Datos_CMg!$D$770 -> 2022 | C36: =(SMALL(Datos_CMg!$C$779:$C$787,1)+SMALL(Datos_CMg!$C$779:$C$787,2)+SMALL(Datos_CMg!$C$779:$C$787,3)+SMALL(Datos_CMg!$C$779:$C$787,4))/4 -> 0.045 | D36: =(LARGE($F36:$M36,1)+LARGE($F36:$M36,2)+LARGE($F36:$M36,3)+LARGE($F36:$M36,4))/4 -> 177.7325 | E36: =D36-C36 -> 177.6875 | F36: =LARGE(Datos_CMg!$C$789:$C$793,1) -> 139.51 | G36: =LARGE(Datos_CMg!$C$789:$C$793,2) -> 119.45 | H36: =LARGE(Datos_CMg!$C$789:$C$793,3) -> 97.36 | I36: =LARGE(Datos_CMg!$C$789:$C$793,4) -> 93.02 | J36: =LARGE(Datos_CMg!$C$770:$C$777,1) -> 183.45 | K36: =LARGE(Datos_CMg!$C$770:$C$777,2) -> 183.45 | L36: =LARGE(Datos_CMg!$C$770:$C$777,3) -> 177.02 | M36: =LARGE(Datos_CMg!$C$770:$C$777,4) -> 167.01
A37: 2022-02-03 | B37: =Datos_CMg!$D$794 -> 2022 | C37: =(SMALL(Datos_CMg!$C$803:$C$811,1)+SMALL(Datos_CMg!$C$803:$C$811,2)+SMALL(Datos_CMg!$C$803:$C$811,3)+SMALL(Datos_CMg!$C$803:$C$811,4))/4 -> 34.06 | D37: =(LARGE($F37:$M37,1)+LARGE($F37:$M37,2)+LARGE($F37:$M37,3)+LARGE($F37:$M37,4))/4 -> 111.845 | E37: =D37-C37 -> 77.785 | F37: =LARGE(Datos_CMg!$C$813:$C$817,1) -> 113.9 | G37: =LARGE(Datos_CMg!$C$813:$C$817,2) -> 109.75 | H37: =LARGE(Datos_CMg!$C$813:$C$817,3) -> 108.91 | I37: =LARGE(Datos_CMg!$C$813:$C$817,4) -> 108.42 | J37: =LARGE(Datos_CMg!$C$794:$C$801,1) -> 114.82 | K37: =LARGE(Datos_CMg!$C$794:$C$801,2) -> 106.25 | L37: =LARGE(Datos_CMg!$C$794:$C$801,3) -> 99.55 | M37: =LARGE(Datos_CMg!$C$794:$C$801,4) -> 85.46
A38: 2022-02-04 | B38: =Datos_CMg!$D$818 -> 2022 | C38: =(SMALL(Datos_CMg!$C$827:$C$835,1)+SMALL(Datos_CMg!$C$827:$C$835,2)+SMALL(Datos_CMg!$C$827:$C$835,3)+SMALL(Datos_CMg!$C$827:$C$835,4))/4 -> 25.0975 | D38: =(LARGE($F38:$M38,1)+LARGE($F38:$M38,2)+LARGE($F38:$M38,3)+LARGE($F38:$M38,4))/4 -> 99.595 | E38: =D38-C38 -> 74.4975 | F38: =LARGE(Datos_CMg!$C$837:$C$841,1) -> 94.99 | G38: =LARGE(Datos_CMg!$C$837:$C$841,2) -> 87.73 | H38: =LARGE(Datos_CMg!$C$837:$C$841,3) -> 87.52 | I38: =LARGE(Datos_CMg!$C$837:$C$841,4) -> 86.58 | J38: =LARGE(Datos_CMg!$C$818:$C$825,1) -> 106.26 | K38: =LARGE(Datos_CMg!$C$818:$C$825,2) -> 102.41 | L38: =LARGE(Datos_CMg!$C$818:$C$825,3) -> 94.72 | M38: =LARGE(Datos_CMg!$C$818:$C$825,4) -> 93.63
A39: 2022-02-05 | B39: =Datos_CMg!$D$842 -> 2022 | C39: =(SMALL(Datos_CMg!$C$851:$C$859,1)+SMALL(Datos_CMg!$C$851:$C$859,2)+SMALL(Datos_CMg!$C$851:$C$859,3)+SMALL(Datos_CMg!$C$851:$C$859,4))/4 -> 0 | D39: =(LARGE($F39:$M39,1)+LARGE($F39:$M39,2)+LARGE($F39:$M39,3)+LARGE($F39:$M39,4))/4 -> 83.2575 | E39: =D39-C39 -> 83.2575 | F39: =LARGE(Datos_CMg!$C$861:$C$865,1) -> 82.75 | G39: =LARGE(Datos_CMg!$C$861:$C$865,2) -> 82.75 | H39: =LARGE(Datos_CMg!$C$861:$C$865,3) -> 80.81 | I39: =LARGE(Datos_CMg!$C$861:$C$865,4) -> 80.55 | J39: =LARGE(Datos_CMg!$C$842:$C$849,1) -> 84.59 | K39: =LARGE(Datos_CMg!$C$842:$C$849,2) -> 82.94 | L39: =LARGE(Datos_CMg!$C$842:$C$849,3) -> 81.82 | M39: =LARGE(Datos_CMg!$C$842:$C$849,4) -> 79.35
A40: 2022-02-06 | B40: =Datos_CMg!$D$866 -> 2022 | C40: =(SMALL(Datos_CMg!$C$875:$C$883,1)+SMALL(Datos_CMg!$C$875:$C$883,2)+SMALL(Datos_CMg!$C$875:$C$883,3)+SMALL(Datos_CMg!$C$875:$C$883,4))/4 -> 15.72 | D40: =(LARGE($F40:$M40,1)+LARGE($F40:$M40,2)+LARGE($F40:$M40,3)+LARGE($F40:$M40,4))/4 -> 85.85 | E40: =D40-C40 -> 70.13 | F40: =LARGE(Datos_CMg!$C$885:$C$889,1) -> 86.96 | G40: =LARGE(Datos_CMg!$C$885:$C$889,2) -> 86.54 | H40: =LARGE(Datos_CMg!$C$885:$C$889,3) -> 85.55 | I40: =LARGE(Datos_CMg!$C$885:$C$889,4) -> 84.35 | J40: =LARGE(Datos_CMg!$C$866:$C$873,1) -> 80.9 | K40: =LARGE(Datos_CMg!$C$866:$C$873,2) -> 77.07 | L40: =LARGE(Datos_CMg!$C$866:$C$873,3) -> 75.06 | M40: =LARGE(Datos_CMg!$C$866:$C$873,4) -> 72.59
A41: 2022-02-07 | B41: =Datos_CMg!$D$890 -> 2022 | C41: =(SMALL(Datos_CMg!$C$899:$C$907,1)+SMALL(Datos_CMg!$C$899:$C$907,2)+SMALL(Datos_CMg!$C$899:$C$907,3)+SMALL(Datos_CMg!$C$899:$C$907,4))/4 -> 58.5425 | D41: =(LARGE($F41:$M41,1)+LARGE($F41:$M41,2)+LARGE($F41:$M41,3)+LARGE($F41:$M41,4))/4 -> 86.555 | E41: =D41-C41 -> 28.0125 | F41: =LARGE(Datos_CMg!$C$909:$C$913,1) -> 88.26 | G41: =LARGE(Datos_CMg!$C$909:$C$913,2) -> 88.26 | H41: =LARGE(Datos_CMg!$C$909:$C$913,3) -> 85.49 | I41: =LARGE(Datos_CMg!$C$909:$C$913,4) -> 83.97 | J41: =LARGE(Datos_CMg!$C$890:$C$897,1) -> 84.21 | K41: =LARGE(Datos_CMg!$C$890:$C$897,2) -> 84.11 | L41: =LARGE(Datos_CMg!$C$890:$C$897,3) -> 82.42 | M41: =LARGE(Datos_CMg!$C$890:$C$897,4) -> 80.11
A42: 2022-02-08 | B42: =Datos_CMg!$D$914 -> 2022 | C42: =(SMALL(Datos_CMg!$C$923:$C$931,1)+SMALL(Datos_CMg!$C$923:$C$931,2)+SMALL(Datos_CMg!$C$923:$C$931,3)+SMALL(Datos_CMg!$C$923:$C$931,4))/4 -> 50.4775 | D42: =(LARGE($F42:$M42,1)+LARGE($F42:$M42,2)+LARGE($F42:$M42,3)+LARGE($F42:$M42,4))/4 -> 90.26 | E42: =D42-C42 -> 39.7825 | F42: =LARGE(Datos_CMg!$C$933:$C$937,1) -> 90.26 | G42: =LARGE(Datos_CMg!$C$933:$C$937,2) -> 90.26 | H42: =LARGE(Datos_CMg!$C$933:$C$937,3) -> 90.26 | I42: =LARGE(Datos_CMg!$C$933:$C$937,4) -> 90.26 | J42: =LARGE(Datos_CMg!$C$914:$C$921,1) -> 85.29 | K42: =LARGE(Datos_CMg!$C$914:$C$921,2) -> 85.29 | L42: =LARGE(Datos_CMg!$C$914:$C$921,3) -> 85.29 | M42: =LARGE(Datos_CMg!$C$914:$C$921,4) -> 84.5
A43: 2022-02-09 | B43: =Datos_CMg!$D$938 -> 2022 | C43: =(SMALL(Datos_CMg!$C$947:$C$955,1)+SMALL(Datos_CMg!$C$947:$C$955,2)+SMALL(Datos_CMg!$C$947:$C$955,3)+SMALL(Datos_CMg!$C$947:$C$955,4))/4 -> 49.31 | D43: =(LARGE($F43:$M43,1)+LARGE($F43:$M43,2)+LARGE($F43:$M43,3)+LARGE($F43:$M43,4))/4 -> 92.56 | E43: =D43-C43 -> 43.25 | F43: =LARGE(Datos_CMg!$C$957:$C$961,1) -> 92.56 | G43: =LARGE(Datos_CMg!$C$957:$C$961,2) -> 92.56 | H43: =LARGE(Datos_CMg!$C$957:$C$961,3) -> 92.56 | I43: =LARGE(Datos_CMg!$C$957:$C$961,4) -> 92.56 | J43: =LARGE(Datos_CMg!$C$938:$C$945,1) -> 88.73 | K43: =LARGE(Datos_CMg!$C$938:$C$945,2) -> 88.73 | L43: =LARGE(Datos_CMg!$C$938:$C$945,3) -> 88.73 | M43: =LARGE(Datos_CMg!$C$938:$C$945,4) -> 88.73
A44: 2022-02-10 | B44: =Datos_CMg!$D$962 -> 2022 | C44: =(SMALL(Datos_CMg!$C$971:$C$979,1)+SMALL(Datos_CMg!$C$971:$C$979,2)+SMALL(Datos_CMg!$C$971:$C$979,3)+SMALL(Datos_CMg!$C$971:$C$979,4))/4 -> 36.01 | D44: =(LARGE($F44:$M44,1)+LARGE($F44:$M44,2)+LARGE($F44:$M44,3)+LARGE($F44:$M44,4))/4 -> 93.2575 | E44: =D44-C44 -> 57.2475 | F44: =LARGE(Datos_CMg!$C$981:$C$985,1) -> 106.38 | G44: =LARGE(Datos_CMg!$C$981:$C$985,2) -> 92.17 | H44: =LARGE(Datos_CMg!$C$981:$C$985,3) -> 88.7 | I44: =LARGE(Datos_CMg!$C$981:$C$985,4) -> 85.78 | J44: =LARGE(Datos_CMg!$C$962:$C$969,1) -> 85.2 | K44: =LARGE(Datos_CMg!$C$962:$C$969,2) -> 80.19 | L44: =LARGE(Datos_CMg!$C$962:$C$969,3) -> 78.77 | M44: =LARGE(Datos_CMg!$C$962:$C$969,4) -> 76.89
A45: 2022-02-11 | B45: =Datos_CMg!$D$986 -> 2022 | C45: =(SMALL(Datos_CMg!$C$995:$C$1003,1)+SMALL(Datos_CMg!$C$995:$C$1003,2)+SMALL(Datos_CMg!$C$995:$C$1003,3)+SMALL(Datos_CMg!$C$995:$C$1003,4))/4 -> 0 | D45: =(LARGE($F45:$M45,1)+LARGE($F45:$M45,2)+LARGE($F45:$M45,3)+LARGE($F45:$M45,4))/4 -> 89.8225 | E45: =D45-C45 -> 89.8225 | F45: =LARGE(Datos_CMg!$C$1005:$C$1009,1) -> 92.04 | G45: =LARGE(Datos_CMg!$C$1005:$C$1009,2) -> 89.18 | H45: =LARGE(Datos_CMg!$C$1005:$C$1009,3) -> 84.17 | I45: =LARGE(Datos_CMg!$C$1005:$C$1009,4) -> 80.29 | J45: =LARGE(Datos_CMg!$C$986:$C$993,1) -> 89.12 | K45: =LARGE(Datos_CMg!$C$986:$C$993,2) -> 88.95 | L45: =LARGE(Datos_CMg!$C$986:$C$993,3) -> 88.1 | M45: =LARGE(Datos_CMg!$C$986:$C$993,4) -> 86.1
A46: 2022-02-12 | B46: =Datos_CMg!$D$1010 -> 2022 | C46: =(SMALL(Datos_CMg!$C$1019:$C$1027,1)+SMALL(Datos_CMg!$C$1019:$C$1027,2)+SMALL(Datos_CMg!$C$1019:$C$1027,3)+SMALL(Datos_CMg!$C$1019:$C$1027,4))/4 -> 0 | D46: =(LARGE($F46:$M46,1)+LARGE($F46:$M46,2)+LARGE($F46:$M46,3)+LARGE($F46:$M46,4))/4 -> 95.355 | E46: =D46-C46 -> 95.355 | F46: =LARGE(Datos_CMg!$C$1029:$C$1033,1) -> 98.63 | G46: =LARGE(Datos_CMg!$C$1029:$C$1033,2) -> 98.63 | H46: =LARGE(Datos_CMg!$C$1029:$C$1033,3) -> 85.65 | I46: =LARGE(Datos_CMg!$C$1029:$C$1033,4) -> 82.46 | J46: =LARGE(Datos_CMg!$C$1010:$C$1017,1) -> 92.08 | K46: =LARGE(Datos_CMg!$C$1010:$C$1017,2) -> 92.08 | L46: =LARGE(Datos_CMg!$C$1010:$C$1017,3) -> 92.08 | M46: =LARGE(Datos_CMg!$C$1010:$C$1017,4) -> 91.88
A47: 2022-02-13 | B47: =Datos_CMg!$D$1034 -> 2022 | C47: =(SMALL(Datos_CMg!$C$1043:$C$1051,1)+SMALL(Datos_CMg!$C$1043:$C$1051,2)+SMALL(Datos_CMg!$C$1043:$C$1051,3)+SMALL(Datos_CMg!$C$1043:$C$1051,4))/4 -> 0 | D47: =(LARGE($F47:$M47,1)+LARGE($F47:$M47,2)+LARGE($F47:$M47,3)+LARGE($F47:$M47,4))/4 -> 116.5425 | E47: =D47-C47 -> 116.5425 | F47: =LARGE(Datos_CMg!$C$1053:$C$1057,1) -> 117 | G47: =LARGE(Datos_CMg!$C$1053:$C$1057,2) -> 117 | H47: =LARGE(Datos_CMg!$C$1053:$C$1057,3) -> 114.97 | I47: =LARGE(Datos_CMg!$C$1053:$C$1057,4) -> 104.62 | J47: =LARGE(Datos_CMg!$C$1034:$C$1041,1) -> 117.2 | K47: =LARGE(Datos_CMg!$C$1034:$C$1041,2) -> 101.5 | L47: =LARGE(Datos_CMg!$C$1034:$C$1041,3) -> 99.59 | M47: =LARGE(Datos_CMg!$C$1034:$C$1041,4) -> 95.36
A48: 2022-02-14 | B48: =Datos_CMg!$D$1058 -> 2022 | C48: =(SMALL(Datos_CMg!$C$1067:$C$1075,1)+SMALL(Datos_CMg!$C$1067:$C$1075,2)+SMALL(Datos_CMg!$C$1067:$C$1075,3)+SMALL(Datos_CMg!$C$1067:$C$1075,4))/4 -> 58.27 | D48: =(LARGE($F48:$M48,1)+LARGE($F48:$M48,2)+LARGE($F48:$M48,3)+LARGE($F48:$M48,4))/4 -> 216.5775 | E48: =D48-C48 -> 158.3075 | F48: =LARGE(Datos_CMg!$C$1077:$C$1081,1) -> 183.85 | G48: =LARGE(Datos_CMg!$C$1077:$C$1081,2) -> 183.85 | H48: =LARGE(Datos_CMg!$C$1077:$C$1081,3) -> 183.85 | I48: =LARGE(Datos_CMg!$C$1077:$C$1081,4) -> 140.32 | J48: =LARGE(Datos_CMg!$C$1058:$C$1065,1) -> 251.85 | K48: =LARGE(Datos_CMg!$C$1058:$C$1065,2) -> 246.76 | L48: =LARGE(Datos_CMg!$C$1058:$C$1065,3) -> 179.12 | M48: =LARGE(Datos_CMg!$C$1058:$C$1065,4) -> 179.12
A49: 2022-02-15 | B49: =Datos_CMg!$D$1082 -> 2022 | C49: =(SMALL(Datos_CMg!$C$1091:$C$1099,1)+SMALL(Datos_CMg!$C$1091:$C$1099,2)+SMALL(Datos_CMg!$C$1091:$C$1099,3)+SMALL(Datos_CMg!$C$1091:$C$1099,4))/4 -> 54.84 | D49: =(LARGE($F49:$M49,1)+LARGE($F49:$M49,2)+LARGE($F49:$M49,3)+LARGE($F49:$M49,4))/4 -> 189.25 | E49: =D49-C49 -> 134.41 | F49: =LARGE(Datos_CMg!$C$1101:$C$1105,1) -> 189.25 | G49: =LARGE(Datos_CMg!$C$1101:$C$1105,2) -> 189.25 | H49: =LARGE(Datos_CMg!$C$1101:$C$1105,3) -> 189.25 | I49: =LARGE(Datos_CMg!$C$1101:$C$1105,4) -> 189.25 | J49: =LARGE(Datos_CMg!$C$1082:$C$1089,1) -> 141.89 | K49: =LARGE(Datos_CMg!$C$1082:$C$1089,2) -> 103.79 | L49: =LARGE(Datos_CMg!$C$1082:$C$1089,3) -> 96.85 | M49: =LARGE(Datos_CMg!$C$1082:$C$1089,4) -> 87.14
A50: 2022-02-16 | B50: =Datos_CMg!$D$1106 -> 2022 | C50: =(SMALL(Datos_CMg!$C$1115:$C$1123,1)+SMALL(Datos_CMg!$C$1115:$C$1123,2)+SMALL(Datos_CMg!$C$1115:$C$1123,3)+SMALL(Datos_CMg!$C$1115:$C$1123,4))/4 -> 4.4775 | D50: =(LARGE($F50:$M50,1)+LARGE($F50:$M50,2)+LARGE($F50:$M50,3)+LARGE($F50:$M50,4))/4 -> 136.495 | E50: =D50-C50 -> 132.0175 | F50: =LARGE(Datos_CMg!$C$1125:$C$1129,1) -> 88.55 | G50: =LARGE(Datos_CMg!$C$1125:$C$1129,2) -> 87.9 | H50: =LARGE(Datos_CMg!$C$1125:$C$1129,3) -> 87.12 | I50: =LARGE(Datos_CMg!$C$1125:$C$1129,4) -> 87.12 | J50: =LARGE(Datos_CMg!$C$1106:$C$1113,1) -> 181.46 | K50: =LARGE(Datos_CMg!$C$1106:$C$1113,2) -> 181.46 | L50: =LARGE(Datos_CMg!$C$1106:$C$1113,3) -> 94.51 | M50: =LARGE(Datos_CMg!$C$1106:$C$1113,4) -> 86.77
A51: 2022-02-17 | B51: =Datos_CMg!$D$1130 -> 2022 | C51: =(SMALL(Datos_CMg!$C$1139:$C$1147,1)+SMALL(Datos_CMg!$C$1139:$C$1147,2)+SMALL(Datos_CMg!$C$1139:$C$1147,3)+SMALL(Datos_CMg!$C$1139:$C$1147,4))/4 -> 39.58 | D51: =(LARGE($F51:$M51,1)+LARGE($F51:$M51,2)+LARGE($F51:$M51,3)+LARGE($F51:$M51,4))/4 -> 102.87 | E51: =D51-C51 -> 63.29 | F51: =LARGE(Datos_CMg!$C$1149:$C$1153,1) -> 107.31 | G51: =LARGE(Datos_CMg!$C$1149:$C$1153,2) -> 102.7 | H51: =LARGE(Datos_CMg!$C$1149:$C$1153,3) -> 95.62 | I51: =LARGE(Datos_CMg!$C$1149:$C$1153,4) -> 94.96 | J51: =LARGE(Datos_CMg!$C$1130:$C$1137,1) -> 105.85 | K51: =LARGE(Datos_CMg!$C$1130:$C$1137,2) -> 86.19 | L51: =LARGE(Datos_CMg!$C$1130:$C$1137,3) -> 83.44 | M51: =LARGE(Datos_CMg!$C$1130:$C$1137,4) -> 77.14
A52: 2022-02-18 | B52: =Datos_CMg!$D$1154 -> 2022 | C52: =(SMALL(Datos_CMg!$C$1163:$C$1171,1)+SMALL(Datos_CMg!$C$1163:$C$1171,2)+SMALL(Datos_CMg!$C$1163:$C$1171,3)+SMALL(Datos_CMg!$C$1163:$C$1171,4))/4 -> 37.91 | D52: =(LARGE($F52:$M52,1)+LARGE($F52:$M52,2)+LARGE($F52:$M52,3)+LARGE($F52:$M52,4))/4 -> 173.44 | E52: =D52-C52 -> 135.53 | F52: =LARGE(Datos_CMg!$C$1173:$C$1177,1) -> 185.68 | G52: =LARGE(Datos_CMg!$C$1173:$C$1177,2) -> 143.32 | H52: =LARGE(Datos_CMg!$C$1173:$C$1177,3) -> 107.9 | I52: =LARGE(Datos_CMg!$C$1173:$C$1177,4) -> 82.88 | J52: =LARGE(Datos_CMg!$C$1154:$C$1161,1) -> 182.38 | K52: =LARGE(Datos_CMg!$C$1154:$C$1161,2) -> 182.38 | L52: =LARGE(Datos_CMg!$C$1154:$C$1161,3) -> 127.76 | M52: =LARGE(Datos_CMg!$C$1154:$C$1161,4) -> 105.37
A53: 2022-02-19 | B53: =Datos_CMg!$D$1178 -> 2022 | C53: =(SMALL(Datos_CMg!$C$1187:$C$1195,1)+SMALL(Datos_CMg!$C$1187:$C$1195,2)+SMALL(Datos_CMg!$C$1187:$C$1195,3)+SMALL(Datos_CMg!$C$1187:$C$1195,4))/4 -> 0 | D53: =(LARGE($F53:$M53,1)+LARGE($F53:$M53,2)+LARGE($F53:$M53,3)+LARGE($F53:$M53,4))/4 -> 148.505 | E53: =D53-C53 -> 148.505 | F53: =LARGE(Datos_CMg!$C$1197:$C$1201,1) -> 110.48 | G53: =LARGE(Datos_CMg!$C$1197:$C$1201,2) -> 110.48 | H53: =LARGE(Datos_CMg!$C$1197:$C$1201,3) -> 106.88 | I53: =LARGE(Datos_CMg!$C$1197:$C$1201,4) -> 104.13 | J53: =LARGE(Datos_CMg!$C$1178:$C$1185,1) -> 154.89 | K53: =LARGE(Datos_CMg!$C$1178:$C$1185,2) -> 154.89 | L53: =LARGE(Datos_CMg!$C$1178:$C$1185,3) -> 150.96 | M53: =LARGE(Datos_CMg!$C$1178:$C$1185,4) -> 133.28
A54: 2022-02-20 | B54: =Datos_CMg!$D$1202 -> 2022 | C54: =(SMALL(Datos_CMg!$C$1211:$C$1219,1)+SMALL(Datos_CMg!$C$1211:$C$1219,2)+SMALL(Datos_CMg!$C$1211:$C$1219,3)+SMALL(Datos_CMg!$C$1211:$C$1219,4))/4 -> 0 | D54: =(LARGE($F54:$M54,1)+LARGE($F54:$M54,2)+LARGE($F54:$M54,3)+LARGE($F54:$M54,4))/4 -> 106.2575 | E54: =D54-C54 -> 106.2575 | F54: =LARGE(Datos_CMg!$C$1221:$C$1225,1) -> 112.61 | G54: =LARGE(Datos_CMg!$C$1221:$C$1225,2) -> 108.17 | H54: =LARGE(Datos_CMg!$C$1221:$C$1225,3) -> 102.91 | I54: =LARGE(Datos_CMg!$C$1221:$C$1225,4) -> 85.13 | J54: =LARGE(Datos_CMg!$C$1202:$C$1209,1) -> 101.34 | K54: =LARGE(Datos_CMg!$C$1202:$C$1209,2) -> 96.44 | L54: =LARGE(Datos_CMg!$C$1202:$C$1209,3) -> 94.33 | M54: =LARGE(Datos_CMg!$C$1202:$C$1209,4) -> 92.88
A55: 2022-02-21 | B55: =Datos_CMg!$D$1226 -> 2022 | C55: =(SMALL(Datos_CMg!$C$1235:$C$1243,1)+SMALL(Datos_CMg!$C$1235:$C$1243,2)+SMALL(Datos_CMg!$C$1235:$C$1243,3)+SMALL(Datos_CMg!$C$1235:$C$1243,4))/4 -> 38.6675 | D55: =(LARGE($F55:$M55,1)+LARGE($F55:$M55,2)+LARGE($F55:$M55,3)+LARGE($F55:$M55,4))/4 -> 181.6525 | E55: =D55-C55 -> 142.985 | F55: =LARGE(Datos_CMg!$C$1245:$C$1249,1) -> 272.58 | G55: =LARGE(Datos_CMg!$C$1245:$C$1249,2) -> 177.1 | H55: =LARGE(Datos_CMg!$C$1245:$C$1249,3) -> 156.18 | I55: =LARGE(Datos_CMg!$C$1245:$C$1249,4) -> 120.75 | J55: =LARGE(Datos_CMg!$C$1226:$C$1233,1) -> 117.28 | K55: =LARGE(Datos_CMg!$C$1226:$C$1233,2) -> 115 | L55: =LARGE(Datos_CMg!$C$1226:$C$1233,3) -> 115 | M55: =LARGE(Datos_CMg!$C$1226:$C$1233,4) -> 115
A56: 2022-02-22 | B56: =Datos_CMg!$D$1250 -> 2022 | C56: =(SMALL(Datos_CMg!$C$1259:$C$1267,1)+SMALL(Datos_CMg!$C$1259:$C$1267,2)+SMALL(Datos_CMg!$C$1259:$C$1267,3)+SMALL(Datos_CMg!$C$1259:$C$1267,4))/4 -> 45.3525 | D56: =(LARGE($F56:$M56,1)+LARGE($F56:$M56,2)+LARGE($F56:$M56,3)+LARGE($F56:$M56,4))/4 -> 118.6 | E56: =D56-C56 -> 73.2475 | F56: =LARGE(Datos_CMg!$C$1269:$C$1273,1) -> 118.6 | G56: =LARGE(Datos_CMg!$C$1269:$C$1273,2) -> 118.6 | H56: =LARGE(Datos_CMg!$C$1269:$C$1273,3) -> 118.6 | I56: =LARGE(Datos_CMg!$C$1269:$C$1273,4) -> 118.6 | J56: =LARGE(Datos_CMg!$C$1250:$C$1257,1) -> 113.38 | K56: =LARGE(Datos_CMg!$C$1250:$C$1257,2) -> 113.38 | L56: =LARGE(Datos_CMg!$C$1250:$C$1257,3) -> 113.38 | M56: =LARGE(Datos_CMg!$C$1250:$C$1257,4) -> 113.38
A57: 2022-02-23 | B57: =Datos_CMg!$D$1274 -> 2022 | C57: =(SMALL(Datos_CMg!$C$1283:$C$1291,1)+SMALL(Datos_CMg!$C$1283:$C$1291,2)+SMALL(Datos_CMg!$C$1283:$C$1291,3)+SMALL(Datos_CMg!$C$1283:$C$1291,4))/4 -> 44.81 | D57: =(LARGE($F57:$M57,1)+LARGE($F57:$M57,2)+LARGE($F57:$M57,3)+LARGE($F57:$M57,4))/4 -> 186.365 | E57: =D57-C57 -> 141.555 | F57: =LARGE(Datos_CMg!$C$1293:$C$1297,1) -> 198.58 | G57: =LARGE(Datos_CMg!$C$1293:$C$1297,2) -> 176.89 | H57: =LARGE(Datos_CMg!$C$1293:$C$1297,3) -> 175.78 | I57: =LARGE(Datos_CMg!$C$1293:$C$1297,4) -> 119.55 | J57: =LARGE(Datos_CMg!$C$1274:$C$1281,1) -> 194.21 | K57: =LARGE(Datos_CMg!$C$1274:$C$1281,2) -> 169.56 | L57: =LARGE(Datos_CMg!$C$1274:$C$1281,3) -> 165.21 | M57: =LARGE(Datos_CMg!$C$1274:$C$1281,4) -> 165.21
A58: 2022-02-24 | B58: =Datos_CMg!$D$1298 -> 2022 | C58: =(SMALL(Datos_CMg!$C$1307:$C$1315,1)+SMALL(Datos_CMg!$C$1307:$C$1315,2)+SMALL(Datos_CMg!$C$1307:$C$1315,3)+SMALL(Datos_CMg!$C$1307:$C$1315,4))/4 -> 0 | D58: =(LARGE($F58:$M58,1)+LARGE($F58:$M58,2)+LARGE($F58:$M58,3)+LARGE($F58:$M58,4))/4 -> 109.355 | E58: =D58-C58 -> 109.355 | F58: =LARGE(Datos_CMg!$C$1317:$C$1321,1) -> 97.22 | G58: =LARGE(Datos_CMg!$C$1317:$C$1321,2) -> 97.22 | H58: =LARGE(Datos_CMg!$C$1317:$C$1321,3) -> 85.13 | I58: =LARGE(Datos_CMg!$C$1317:$C$1321,4) -> 82.35 | J58: =LARGE(Datos_CMg!$C$1298:$C$1305,1) -> 112.48 | K58: =LARGE(Datos_CMg!$C$1298:$C$1305,2) -> 112.48 | L58: =LARGE(Datos_CMg!$C$1298:$C$1305,3) -> 112.2 | M58: =LARGE(Datos_CMg!$C$1298:$C$1305,4) -> 100.26
A59: 2022-02-25 | B59: =Datos_CMg!$D$1322 -> 2022 | C59: =(SMALL(Datos_CMg!$C$1331:$C$1339,1)+SMALL(Datos_CMg!$C$1331:$C$1339,2)+SMALL(Datos_CMg!$C$1331:$C$1339,3)+SMALL(Datos_CMg!$C$1331:$C$1339,4))/4 -> 28.125 | D59: =(LARGE($F59:$M59,1)+LARGE($F59:$M59,2)+LARGE($F59:$M59,3)+LARGE($F59:$M59,4))/4 -> 120.92 | E59: =D59-C59 -> 92.795 | F59: =LARGE(Datos_CMg!$C$1341:$C$1345,1) -> 111.03 | G59: =LARGE(Datos_CMg!$C$1341:$C$1345,2) -> 95.74 | H59: =LARGE(Datos_CMg!$C$1341:$C$1345,3) -> 95.4 | I59: =LARGE(Datos_CMg!$C$1341:$C$1345,4) -> 90.64 | J59: =LARGE(Datos_CMg!$C$1322:$C$1329,1) -> 120.92 | K59: =LARGE(Datos_CMg!$C$1322:$C$1329,2) -> 120.92 | L59: =LARGE(Datos_CMg!$C$1322:$C$1329,3) -> 120.92 | M59: =LARGE(Datos_CMg!$C$1322:$C$1329,4) -> 120.92
A60: 2022-02-26 | B60: =Datos_CMg!$D$1346 -> 2022 | C60: =(SMALL(Datos_CMg!$C$1355:$C$1363,1)+SMALL(Datos_CMg!$C$1355:$C$1363,2)+SMALL(Datos_CMg!$C$1355:$C$1363,3)+SMALL(Datos_CMg!$C$1355:$C$1363,4))/4 -> 0 | D60: =(LARGE($F60:$M60,1)+LARGE($F60:$M60,2)+LARGE($F60:$M60,3)+LARGE($F60:$M60,4))/4 -> 99.925 | E60: =D60-C60 -> 99.925 | F60: =LARGE(Datos_CMg!$C$1365:$C$1369,1) -> 104.2 | G60: =LARGE(Datos_CMg!$C$1365:$C$1369,2) -> 83.69 | H60: =LARGE(Datos_CMg!$C$1365:$C$1369,3) -> 80.28 | I60: =LARGE(Datos_CMg!$C$1365:$C$1369,4) -> 77.65 | J60: =LARGE(Datos_CMg!$C$1346:$C$1353,1) -> 99.22 | K60: =LARGE(Datos_CMg!$C$1346:$C$1353,2) -> 99.22 | L60: =LARGE(Datos_CMg!$C$1346:$C$1353,3) -> 97.06 | M60: =LARGE(Datos_CMg!$C$1346:$C$1353,4) -> 86.85
A61: 2022-02-27 | B61: =Datos_CMg!$D$1370 -> 2022 | C61: =(SMALL(Datos_CMg!$C$1379:$C$1387,1)+SMALL(Datos_CMg!$C$1379:$C$1387,2)+SMALL(Datos_CMg!$C$1379:$C$1387,3)+SMALL(Datos_CMg!$C$1379:$C$1387,4))/4 -> 0 | D61: =(LARGE($F61:$M61,1)+LARGE($F61:$M61,2)+LARGE($F61:$M61,3)+LARGE($F61:$M61,4))/4 -> 78.775 | E61: =D61-C61 -> 78.775 | F61: =LARGE(Datos_CMg!$C$1389:$C$1393,1) -> 82.64 | G61: =LARGE(Datos_CMg!$C$1389:$C$1393,2) -> 82.62 | H61: =LARGE(Datos_CMg!$C$1389:$C$1393,3) -> 73.57 | I61: =LARGE(Datos_CMg!$C$1389:$C$1393,4) -> 72.06 | J61: =LARGE(Datos_CMg!$C$1370:$C$1377,1) -> 74.92 | K61: =LARGE(Datos_CMg!$C$1370:$C$1377,2) -> 74.92 | L61: =LARGE(Datos_CMg!$C$1370:$C$1377,3) -> 74.92 | M61: =LARGE(Datos_CMg!$C$1370:$C$1377,4) -> 74.92
A62: 2022-02-28 | B62: =Datos_CMg!$D$1394 -> 2022 | C62: =(SMALL(Datos_CMg!$C$1403:$C$1411,1)+SMALL(Datos_CMg!$C$1403:$C$1411,2)+SMALL(Datos_CMg!$C$1403:$C$1411,3)+SMALL(Datos_CMg!$C$1403:$C$1411,4))/4 -> 0 | D62: =(LARGE($F62:$M62,1)+LARGE($F62:$M62,2)+LARGE($F62:$M62,3)+LARGE($F62:$M62,4))/4 -> 88.3025 | E62: =D62-C62 -> 88.3025 | F62: =LARGE(Datos_CMg!$C$1413:$C$1417,1) -> 89.43 | G62: =LARGE(Datos_CMg!$C$1413:$C$1417,2) -> 81.84 | H62: =LARGE(Datos_CMg!$C$1413:$C$1417,3) -> 81.84 | I62: =LARGE(Datos_CMg!$C$1413:$C$1417,4) -> 5.96 | J62: =LARGE(Datos_CMg!$C$1394:$C$1401,1) -> 92.44 | K62: =LARGE(Datos_CMg!$C$1394:$C$1401,2) -> 89.22 | L62: =LARGE(Datos_CMg!$C$1394:$C$1401,3) -> 82.12 | M62: =LARGE(Datos_CMg!$C$1394:$C$1401,4) -> 72.01
A63: 2022-03-01 | B63: =Datos_CMg!$D$1418 -> 2022 | C63: =(SMALL(Datos_CMg!$C$1427:$C$1435,1)+SMALL(Datos_CMg!$C$1427:$C$1435,2)+SMALL(Datos_CMg!$C$1427:$C$1435,3)+SMALL(Datos_CMg!$C$1427:$C$1435,4))/4 -> 46.3925 | D63: =(LARGE($F63:$M63,1)+LARGE($F63:$M63,2)+LARGE($F63:$M63,3)+LARGE($F63:$M63,4))/4 -> 161.305 | E63: =D63-C63 -> 114.9125 | F63: =LARGE(Datos_CMg!$C$1437:$C$1441,1) -> 199.98 | G63: =LARGE(Datos_CMg!$C$1437:$C$1441,2) -> 187.38 | H63: =LARGE(Datos_CMg!$C$1437:$C$1441,3) -> 132.21 | I63: =LARGE(Datos_CMg!$C$1437:$C$1441,4) -> 125.65 | J63: =LARGE(Datos_CMg!$C$1418:$C$1425,1) -> 115.71 | K63: =LARGE(Datos_CMg!$C$1418:$C$1425,2) -> 94.41 | L63: =LARGE(Datos_CMg!$C$1418:$C$1425,3) -> 84.97 | M63: =LARGE(Datos_CMg!$C$1418:$C$1425,4) -> 81.03
A64: 2022-03-02 | B64: =Datos_CMg!$D$1442 -> 2022 | C64: =(SMALL(Datos_CMg!$C$1451:$C$1459,1)+SMALL(Datos_CMg!$C$1451:$C$1459,2)+SMALL(Datos_CMg!$C$1451:$C$1459,3)+SMALL(Datos_CMg!$C$1451:$C$1459,4))/4 -> 0 | D64: =(LARGE($F64:$M64,1)+LARGE($F64:$M64,2)+LARGE($F64:$M64,3)+LARGE($F64:$M64,4))/4 -> 118.62 | E64: =D64-C64 -> 118.62 | F64: =LARGE(Datos_CMg!$C$1461:$C$1465,1) -> 121.03 | G64: =LARGE(Datos_CMg!$C$1461:$C$1465,2) -> 118.31 | H64: =LARGE(Datos_CMg!$C$1461:$C$1465,3) -> 116.07 | I64: =LARGE(Datos_CMg!$C$1461:$C$1465,4) -> 113.83 | J64: =LARGE(Datos_CMg!$C$1442:$C$1449,1) -> 117.67 | K64: =LARGE(Datos_CMg!$C$1442:$C$1449,2) -> 117.47 | L64: =LARGE(Datos_CMg!$C$1442:$C$1449,3) -> 106.97 | M64: =LARGE(Datos_CMg!$C$1442:$C$1449,4) -> 105.23
A65: 2022-03-03 | B65: =Datos_CMg!$D$1466 -> 2022 | C65: =(SMALL(Datos_CMg!$C$1475:$C$1483,1)+SMALL(Datos_CMg!$C$1475:$C$1483,2)+SMALL(Datos_CMg!$C$1475:$C$1483,3)+SMALL(Datos_CMg!$C$1475:$C$1483,4))/4 -> 78.8725 | D65: =(LARGE($F65:$M65,1)+LARGE($F65:$M65,2)+LARGE($F65:$M65,3)+LARGE($F65:$M65,4))/4 -> 202.6925 | E65: =D65-C65 -> 123.82 | F65: =LARGE(Datos_CMg!$C$1485:$C$1489,1) -> 253.88 | G65: =LARGE(Datos_CMg!$C$1485:$C$1489,2) -> 199.59 | H65: =LARGE(Datos_CMg!$C$1485:$C$1489,3) -> 199.59 | I65: =LARGE(Datos_CMg!$C$1485:$C$1489,4) -> 157.71 | J65: =LARGE(Datos_CMg!$C$1466:$C$1473,1) -> 117.81 | K65: =LARGE(Datos_CMg!$C$1466:$C$1473,2) -> 117.81 | L65: =LARGE(Datos_CMg!$C$1466:$C$1473,3) -> 116.22 | M65: =LARGE(Datos_CMg!$C$1466:$C$1473,4) -> 116.11
A66: 2022-03-04 | B66: =Datos_CMg!$D$1490 -> 2022 | C66: =(SMALL(Datos_CMg!$C$1499:$C$1507,1)+SMALL(Datos_CMg!$C$1499:$C$1507,2)+SMALL(Datos_CMg!$C$1499:$C$1507,3)+SMALL(Datos_CMg!$C$1499:$C$1507,4))/4 -> 57.4775 | D66: =(LARGE($F66:$M66,1)+LARGE($F66:$M66,2)+LARGE($F66:$M66,3)+LARGE($F66:$M66,4))/4 -> 196.26 | E66: =D66-C66 -> 138.7825 | F66: =LARGE(Datos_CMg!$C$1509:$C$1513,1) -> 127.09 | G66: =LARGE(Datos_CMg!$C$1509:$C$1513,2) -> 127.09 | H66: =LARGE(Datos_CMg!$C$1509:$C$1513,3) -> 127.09 | I66: =LARGE(Datos_CMg!$C$1509:$C$1513,4) -> 107.66 | J66: =LARGE(Datos_CMg!$C$1490:$C$1497,1) -> 196.26 | K66: =LARGE(Datos_CMg!$C$1490:$C$1497,2) -> 196.26 | L66: =LARGE(Datos_CMg!$C$1490:$C$1497,3) -> 196.26 | M66: =LARGE(Datos_CMg!$C$1490:$C$1497,4) -> 196.26
A67: 2022-03-05 | B67: =Datos_CMg!$D$1514 -> 2022 | C67: =(SMALL(Datos_CMg!$C$1523:$C$1531,1)+SMALL(Datos_CMg!$C$1523:$C$1531,2)+SMALL(Datos_CMg!$C$1523:$C$1531,3)+SMALL(Datos_CMg!$C$1523:$C$1531,4))/4 -> 0 | D67: =(LARGE($F67:$M67,1)+LARGE($F67:$M67,2)+LARGE($F67:$M67,3)+LARGE($F67:$M67,4))/4 -> 119.735 | E67: =D67-C67 -> 119.735 | F67: =LARGE(Datos_CMg!$C$1533:$C$1537,1) -> 117.53 | G67: =LARGE(Datos_CMg!$C$1533:$C$1537,2) -> 117.53 | H67: =LARGE(Datos_CMg!$C$1533:$C$1537,3) -> 115.73 | I67: =LARGE(Datos_CMg!$C$1533:$C$1537,4) -> 93.15 | J67: =LARGE(Datos_CMg!$C$1514:$C$1521,1) -> 119.94 | K67: =LARGE(Datos_CMg!$C$1514:$C$1521,2) -> 119.94 | L67: =LARGE(Datos_CMg!$C$1514:$C$1521,3) -> 119.94 | M67: =LARGE(Datos_CMg!$C$1514:$C$1521,4) -> 119.12
A68: 2022-03-06 | B68: =Datos_CMg!$D$1538 -> 2022 | C68: =(SMALL(Datos_CMg!$C$1547:$C$1555,1)+SMALL(Datos_CMg!$C$1547:$C$1555,2)+SMALL(Datos_CMg!$C$1547:$C$1555,3)+SMALL(Datos_CMg!$C$1547:$C$1555,4))/4 -> 0 | D68: =(LARGE($F68:$M68,1)+LARGE($F68:$M68,2)+LARGE($F68:$M68,3)+LARGE($F68:$M68,4))/4 -> 100.9475 | E68: =D68-C68 -> 100.9475 | F68: =LARGE(Datos_CMg!$C$1557:$C$1561,1) -> 106.58 | G68: =LARGE(Datos_CMg!$C$1557:$C$1561,2) -> 106.58 | H68: =LARGE(Datos_CMg!$C$1557:$C$1561,3) -> 94.99 | I68: =LARGE(Datos_CMg!$C$1557:$C$1561,4) -> 92.69 | J68: =LARGE(Datos_CMg!$C$1538:$C$1545,1) -> 95.64 | K68: =LARGE(Datos_CMg!$C$1538:$C$1545,2) -> 91.08 | L68: =LARGE(Datos_CMg!$C$1538:$C$1545,3) -> 89.44 | M68: =LARGE(Datos_CMg!$C$1538:$C$1545,4) -> 88.86
A69: 2022-03-07 | B69: =Datos_CMg!$D$1562 -> 2022 | C69: =(SMALL(Datos_CMg!$C$1571:$C$1579,1)+SMALL(Datos_CMg!$C$1571:$C$1579,2)+SMALL(Datos_CMg!$C$1571:$C$1579,3)+SMALL(Datos_CMg!$C$1571:$C$1579,4))/4 -> 74.72 | D69: =(LARGE($F69:$M69,1)+LARGE($F69:$M69,2)+LARGE($F69:$M69,3)+LARGE($F69:$M69,4))/4 -> 201.515 | E69: =D69-C69 -> 126.795 | F69: =LARGE(Datos_CMg!$C$1581:$C$1585,1) -> 266.76 | G69: =LARGE(Datos_CMg!$C$1581:$C$1585,2) -> 265.93 | H69: =LARGE(Datos_CMg!$C$1581:$C$1585,3) -> 160.38 | I69: =LARGE(Datos_CMg!$C$1581:$C$1585,4) -> 112.99 | J69: =LARGE(Datos_CMg!$C$1562:$C$1569,1) -> 107.93 | K69: =LARGE(Datos_CMg!$C$1562:$C$1569,2) -> 107.24 | L69: =LARGE(Datos_CMg!$C$1562:$C$1569,3) -> 88.7 | M69: =LARGE(Datos_CMg!$C$1562:$C$1569,4) -> 85.14
A70: 2022-03-08 | B70: =Datos_CMg!$D$1586 -> 2022 | C70: =(SMALL(Datos_CMg!$C$1595:$C$1603,1)+SMALL(Datos_CMg!$C$1595:$C$1603,2)+SMALL(Datos_CMg!$C$1595:$C$1603,3)+SMALL(Datos_CMg!$C$1595:$C$1603,4))/4 -> 0 | D70: =(LARGE($F70:$M70,1)+LARGE($F70:$M70,2)+LARGE($F70:$M70,3)+LARGE($F70:$M70,4))/4 -> 126.035 | E70: =D70-C70 -> 126.035 | F70: =LARGE(Datos_CMg!$C$1605:$C$1609,1) -> 128.85 | G70: =LARGE(Datos_CMg!$C$1605:$C$1609,2) -> 121.2 | H70: =LARGE(Datos_CMg!$C$1605:$C$1609,3) -> 112.33 | I70: =LARGE(Datos_CMg!$C$1605:$C$1609,4) -> 84.75 | J70: =LARGE(Datos_CMg!$C$1586:$C$1593,1) -> 129.22 | K70: =LARGE(Datos_CMg!$C$1586:$C$1593,2) -> 124.27 | L70: =LARGE(Datos_CMg!$C$1586:$C$1593,3) -> 121.8 | M70: =LARGE(Datos_CMg!$C$1586:$C$1593,4) -> 121.8
A71: 2022-03-09 | B71: =Datos_CMg!$D$1610 -> 2022 | C71: =(SMALL(Datos_CMg!$C$1619:$C$1627,1)+SMALL(Datos_CMg!$C$1619:$C$1627,2)+SMALL(Datos_CMg!$C$1619:$C$1627,3)+SMALL(Datos_CMg!$C$1619:$C$1627,4))/4 -> 0 | D71: =(LARGE($F71:$M71,1)+LARGE($F71:$M71,2)+LARGE($F71:$M71,3)+LARGE($F71:$M71,4))/4 -> 124.2125 | E71: =D71-C71 -> 124.2125 | F71: =LARGE(Datos_CMg!$C$1629:$C$1633,1) -> 116.5 | G71: =LARGE(Datos_CMg!$C$1629:$C$1633,2) -> 108.68 | H71: =LARGE(Datos_CMg!$C$1629:$C$1633,3) -> 95.85 | I71: =LARGE(Datos_CMg!$C$1629:$C$1633,4) -> 83.84 | J71: =LARGE(Datos_CMg!$C$1610:$C$1617,1) -> 143.2 | K71: =LARGE(Datos_CMg!$C$1610:$C$1617,2) -> 128.47 | L71: =LARGE(Datos_CMg!$C$1610:$C$1617,3) -> 103 | M71: =LARGE(Datos_CMg!$C$1610:$C$1617,4) -> 85.75
A72: 2022-03-10 | B72: =Datos_CMg!$D$1634 -> 2022 | C72: =(SMALL(Datos_CMg!$C$1643:$C$1651,1)+SMALL(Datos_CMg!$C$1643:$C$1651,2)+SMALL(Datos_CMg!$C$1643:$C$1651,3)+SMALL(Datos_CMg!$C$1643:$C$1651,4))/4 -> 2.9075 | D72: =(LARGE($F72:$M72,1)+LARGE($F72:$M72,2)+LARGE($F72:$M72,3)+LARGE($F72:$M72,4))/4 -> 110.7 | E72: =D72-C72 -> 107.7925 | F72: =LARGE(Datos_CMg!$C$1653:$C$1657,1) -> 108.66 | G72: =LARGE(Datos_CMg!$C$1653:$C$1657,2) -> 108.66 | H72: =LARGE(Datos_CMg!$C$1653:$C$1657,3) -> 108.66 | I72: =LARGE(Datos_CMg!$C$1653:$C$1657,4) -> 94.71 | J72: =LARGE(Datos_CMg!$C$1634:$C$1641,1) -> 116.82 | K72: =LARGE(Datos_CMg!$C$1634:$C$1641,2) -> 104.88 | L72: =LARGE(Datos_CMg!$C$1634:$C$1641,3) -> 77.65 | M72: =LARGE(Datos_CMg!$C$1634:$C$1641,4) -> 76.18
A73: 2022-03-11 | B73: =Datos_CMg!$D$1658 -> 2022 | C73: =(SMALL(Datos_CMg!$C$1667:$C$1675,1)+SMALL(Datos_CMg!$C$1667:$C$1675,2)+SMALL(Datos_CMg!$C$1667:$C$1675,3)+SMALL(Datos_CMg!$C$1667:$C$1675,4))/4 -> 67.4425 | D73: =(LARGE($F73:$M73,1)+LARGE($F73:$M73,2)+LARGE($F73:$M73,3)+LARGE($F73:$M73,4))/4 -> 129.565 | E73: =D73-C73 -> 62.1225 | F73: =LARGE(Datos_CMg!$C$1677:$C$1681,1) -> 130.86 | G73: =LARGE(Datos_CMg!$C$1677:$C$1681,2) -> 130.86 | H73: =LARGE(Datos_CMg!$C$1677:$C$1681,3) -> 129.12 | I73: =LARGE(Datos_CMg!$C$1677:$C$1681,4) -> 127.42 | J73: =LARGE(Datos_CMg!$C$1658:$C$1665,1) -> 122.91 | K73: =LARGE(Datos_CMg!$C$1658:$C$1665,2) -> 111.66 | L73: =LARGE(Datos_CMg!$C$1658:$C$1665,3) -> 101.74 | M73: =LARGE(Datos_CMg!$C$1658:$C$1665,4) -> 93.61
A74: 2022-03-12 | B74: =Datos_CMg!$D$1682 -> 2022 | C74: =(SMALL(Datos_CMg!$C$1691:$C$1699,1)+SMALL(Datos_CMg!$C$1691:$C$1699,2)+SMALL(Datos_CMg!$C$1691:$C$1699,3)+SMALL(Datos_CMg!$C$1691:$C$1699,4))/4 -> 12.7925 | D74: =(LARGE($F74:$M74,1)+LARGE($F74:$M74,2)+LARGE($F74:$M74,3)+LARGE($F74:$M74,4))/4 -> 114.8925 | E74: =D74-C74 -> 102.1 | F74: =LARGE(Datos_CMg!$C$1701:$C$1705,1) -> 119.07 | G74: =LARGE(Datos_CMg!$C$1701:$C$1705,2) -> 117.32 | H74: =LARGE(Datos_CMg!$C$1701:$C$1705,3) -> 112.57 | I74: =LARGE(Datos_CMg!$C$1701:$C$1705,4) -> 110.61 | J74: =LARGE(Datos_CMg!$C$1682:$C$1689,1) -> 106.08 | K74: =LARGE(Datos_CMg!$C$1682:$C$1689,2) -> 106.08 | L74: =LARGE(Datos_CMg!$C$1682:$C$1689,3) -> 105.93 | M74: =LARGE(Datos_CMg!$C$1682:$C$1689,4) -> 105.67
A75: 2022-03-13 | B75: =Datos_CMg!$D$1706 -> 2022 | C75: =(SMALL(Datos_CMg!$C$1715:$C$1723,1)+SMALL(Datos_CMg!$C$1715:$C$1723,2)+SMALL(Datos_CMg!$C$1715:$C$1723,3)+SMALL(Datos_CMg!$C$1715:$C$1723,4))/4 -> 0 | D75: =(LARGE($F75:$M75,1)+LARGE($F75:$M75,2)+LARGE($F75:$M75,3)+LARGE($F75:$M75,4))/4 -> 115.2375 | E75: =D75-C75 -> 115.2375 | F75: =LARGE(Datos_CMg!$C$1725:$C$1729,1) -> 115.85 | G75: =LARGE(Datos_CMg!$C$1725:$C$1729,2) -> 115.7 | H75: =LARGE(Datos_CMg!$C$1725:$C$1729,3) -> 114.84 | I75: =LARGE(Datos_CMg!$C$1725:$C$1729,4) -> 114.56 | J75: =LARGE(Datos_CMg!$C$1706:$C$1713,1) -> 91.03 | K75: =LARGE(Datos_CMg!$C$1706:$C$1713,2) -> 87.46 | L75: =LARGE(Datos_CMg!$C$1706:$C$1713,3) -> 79.85 | M75: =LARGE(Datos_CMg!$C$1706:$C$1713,4) -> 77.5
A76: 2022-03-14 | B76: =Datos_CMg!$D$1730 -> 2022 | C76: =(SMALL(Datos_CMg!$C$1739:$C$1747,1)+SMALL(Datos_CMg!$C$1739:$C$1747,2)+SMALL(Datos_CMg!$C$1739:$C$1747,3)+SMALL(Datos_CMg!$C$1739:$C$1747,4))/4 -> 73.3575 | D76: =(LARGE($F76:$M76,1)+LARGE($F76:$M76,2)+LARGE($F76:$M76,3)+LARGE($F76:$M76,4))/4 -> 224.63 | E76: =D76-C76 -> 151.2725 | F76: =LARGE(Datos_CMg!$C$1749:$C$1753,1) -> 278.86 | G76: =LARGE(Datos_CMg!$C$1749:$C$1753,2) -> 212.65 | H76: =LARGE(Datos_CMg!$C$1749:$C$1753,3) -> 206.34 | I76: =LARGE(Datos_CMg!$C$1749:$C$1753,4) -> 200.67 | J76: =LARGE(Datos_CMg!$C$1730:$C$1737,1) -> 116.64 | K76: =LARGE(Datos_CMg!$C$1730:$C$1737,2) -> 111.13 | L76: =LARGE(Datos_CMg!$C$1730:$C$1737,3) -> 111.13 | M76: =LARGE(Datos_CMg!$C$1730:$C$1737,4) -> 111.13
A77: 2022-03-15 | B77: =Datos_CMg!$D$1754 -> 2022 | C77: =(SMALL(Datos_CMg!$C$1763:$C$1771,1)+SMALL(Datos_CMg!$C$1763:$C$1771,2)+SMALL(Datos_CMg!$C$1763:$C$1771,3)+SMALL(Datos_CMg!$C$1763:$C$1771,4))/4 -> 232.295 | D77: =(LARGE($F77:$M77,1)+LARGE($F77:$M77,2)+LARGE($F77:$M77,3)+LARGE($F77:$M77,4))/4 -> 321.05 | E77: =D77-C77 -> 88.755 | F77: =LARGE(Datos_CMg!$C$1773:$C$1777,1) -> 325.91 | G77: =LARGE(Datos_CMg!$C$1773:$C$1777,2) -> 323.97 | H77: =LARGE(Datos_CMg!$C$1773:$C$1777,3) -> 319.34 | I77: =LARGE(Datos_CMg!$C$1773:$C$1777,4) -> 314.98 | J77: =LARGE(Datos_CMg!$C$1754:$C$1761,1) -> 301.54 | K77: =LARGE(Datos_CMg!$C$1754:$C$1761,2) -> 262.05 | L77: =LARGE(Datos_CMg!$C$1754:$C$1761,3) -> 262.05 | M77: =LARGE(Datos_CMg!$C$1754:$C$1761,4) -> 261.23
A78: 2022-03-16 | B78: =Datos_CMg!$D$1778 -> 2022 | C78: =(SMALL(Datos_CMg!$C$1787:$C$1795,1)+SMALL(Datos_CMg!$C$1787:$C$1795,2)+SMALL(Datos_CMg!$C$1787:$C$1795,3)+SMALL(Datos_CMg!$C$1787:$C$1795,4))/4 -> 261.5775 | D78: =(LARGE($F78:$M78,1)+LARGE($F78:$M78,2)+LARGE($F78:$M78,3)+LARGE($F78:$M78,4))/4 -> 319.235 | E78: =D78-C78 -> 57.6575 | F78: =LARGE(Datos_CMg!$C$1797:$C$1801,1) -> 322.16 | G78: =LARGE(Datos_CMg!$C$1797:$C$1801,2) -> 322.16 | H78: =LARGE(Datos_CMg!$C$1797:$C$1801,3) -> 318.25 | I78: =LARGE(Datos_CMg!$C$1797:$C$1801,4) -> 314.37 | J78: =LARGE(Datos_CMg!$C$1778:$C$1785,1) -> 304.76 | K78: =LARGE(Datos_CMg!$C$1778:$C$1785,2) -> 274.49 | L78: =LARGE(Datos_CMg!$C$1778:$C$1785,3) -> 274.03 | M78: =LARGE(Datos_CMg!$C$1778:$C$1785,4) -> 148.17
A79: 2022-03-17 | B79: =Datos_CMg!$D$1802 -> 2022 | C79: =(SMALL(Datos_CMg!$C$1811:$C$1819,1)+SMALL(Datos_CMg!$C$1811:$C$1819,2)+SMALL(Datos_CMg!$C$1811:$C$1819,3)+SMALL(Datos_CMg!$C$1811:$C$1819,4))/4 -> 76.2825 | D79: =(LARGE($F79:$M79,1)+LARGE($F79:$M79,2)+LARGE($F79:$M79,3)+LARGE($F79:$M79,4))/4 -> 257.645 | E79: =D79-C79 -> 181.3625 | F79: =LARGE(Datos_CMg!$C$1821:$C$1825,1) -> 221.03 | G79: =LARGE(Datos_CMg!$C$1821:$C$1825,2) -> 151.24 | H79: =LARGE(Datos_CMg!$C$1821:$C$1825,3) -> 126.42 | I79: =LARGE(Datos_CMg!$C$1821:$C$1825,4) -> 82.94 | J79: =LARGE(Datos_CMg!$C$1802:$C$1809,1) -> 301.77 | K79: =LARGE(Datos_CMg!$C$1802:$C$1809,2) -> 270.57 | L79: =LARGE(Datos_CMg!$C$1802:$C$1809,3) -> 237.21 | M79: =LARGE(Datos_CMg!$C$1802:$C$1809,4) -> 156.11
A80: 2022-03-18 | B80: =Datos_CMg!$D$1826 -> 2022 | C80: =(SMALL(Datos_CMg!$C$1835:$C$1843,1)+SMALL(Datos_CMg!$C$1835:$C$1843,2)+SMALL(Datos_CMg!$C$1835:$C$1843,3)+SMALL(Datos_CMg!$C$1835:$C$1843,4))/4 -> 58.6325 | D80: =(LARGE($F80:$M80,1)+LARGE($F80:$M80,2)+LARGE($F80:$M80,3)+LARGE($F80:$M80,4))/4 -> 120.2 | E80: =D80-C80 -> 61.5675 | F80: =LARGE(Datos_CMg!$C$1845:$C$1849,1) -> 120.2 | G80: =LARGE(Datos_CMg!$C$1845:$C$1849,2) -> 120.2 | H80: =LARGE(Datos_CMg!$C$1845:$C$1849,3) -> 120.2 | I80: =LARGE(Datos_CMg!$C$1845:$C$1849,4) -> 120.2 | J80: =LARGE(Datos_CMg!$C$1826:$C$1833,1) -> 114.69 | K80: =LARGE(Datos_CMg!$C$1826:$C$1833,2) -> 108.2 | L80: =LARGE(Datos_CMg!$C$1826:$C$1833,3) -> 92.83 | M80: =LARGE(Datos_CMg!$C$1826:$C$1833,4) -> 90.19
A81: 2022-03-19 | B81: =Datos_CMg!$D$1850 -> 2022 | C81: =(SMALL(Datos_CMg!$C$1859:$C$1867,1)+SMALL(Datos_CMg!$C$1859:$C$1867,2)+SMALL(Datos_CMg!$C$1859:$C$1867,3)+SMALL(Datos_CMg!$C$1859:$C$1867,4))/4 -> 85.49 | D81: =(LARGE($F81:$M81,1)+LARGE($F81:$M81,2)+LARGE($F81:$M81,3)+LARGE($F81:$M81,4))/4 -> 128.88 | E81: =D81-C81 -> 43.39 | F81: =LARGE(Datos_CMg!$C$1869:$C$1873,1) -> 130.83 | G81: =LARGE(Datos_CMg!$C$1869:$C$1873,2) -> 130.83 | H81: =LARGE(Datos_CMg!$C$1869:$C$1873,3) -> 128.39 | I81: =LARGE(Datos_CMg!$C$1869:$C$1873,4) -> 125.47 | J81: =LARGE(Datos_CMg!$C$1850:$C$1857,1) -> 115.87 | K81: =LARGE(Datos_CMg!$C$1850:$C$1857,2) -> 115.87 | L81: =LARGE(Datos_CMg!$C$1850:$C$1857,3) -> 112.77 | M81: =LARGE(Datos_CMg!$C$1850:$C$1857,4) -> 102.29
A82: 2022-03-20 | B82: =Datos_CMg!$D$1874 -> 2022 | C82: =(SMALL(Datos_CMg!$C$1883:$C$1891,1)+SMALL(Datos_CMg!$C$1883:$C$1891,2)+SMALL(Datos_CMg!$C$1883:$C$1891,3)+SMALL(Datos_CMg!$C$1883:$C$1891,4))/4 -> 18.2975 | D82: =(LARGE($F82:$M82,1)+LARGE($F82:$M82,2)+LARGE($F82:$M82,3)+LARGE($F82:$M82,4))/4 -> 123.21 | E82: =D82-C82 -> 104.9125 | F82: =LARGE(Datos_CMg!$C$1893:$C$1897,1) -> 125.01 | G82: =LARGE(Datos_CMg!$C$1893:$C$1897,2) -> 122.52 | H82: =LARGE(Datos_CMg!$C$1893:$C$1897,3) -> 122.52 | I82: =LARGE(Datos_CMg!$C$1893:$C$1897,4) -> 119.78 | J82: =LARGE(Datos_CMg!$C$1874:$C$1881,1) -> 122.79 | K82: =LARGE(Datos_CMg!$C$1874:$C$1881,2) -> 121.84 | L82: =LARGE(Datos_CMg!$C$1874:$C$1881,3) -> 121.84 | M82: =LARGE(Datos_CMg!$C$1874:$C$1881,4) -> 121.84
A83: 2022-03-21 | B83: =Datos_CMg!$D$1898 -> 2022 | C83: =(SMALL(Datos_CMg!$C$1907:$C$1915,1)+SMALL(Datos_CMg!$C$1907:$C$1915,2)+SMALL(Datos_CMg!$C$1907:$C$1915,3)+SMALL(Datos_CMg!$C$1907:$C$1915,4))/4 -> 104.0625 | D83: =(LARGE($F83:$M83,1)+LARGE($F83:$M83,2)+LARGE($F83:$M83,3)+LARGE($F83:$M83,4))/4 -> 144.65 | E83: =D83-C83 -> 40.5875 | F83: =LARGE(Datos_CMg!$C$1917:$C$1921,1) -> 140.2 | G83: =LARGE(Datos_CMg!$C$1917:$C$1921,2) -> 133.67 | H83: =LARGE(Datos_CMg!$C$1917:$C$1921,3) -> 123.04 | I83: =LARGE(Datos_CMg!$C$1917:$C$1921,4) -> 94.42 | J83: =LARGE(Datos_CMg!$C$1898:$C$1905,1) -> 154.04 | K83: =LARGE(Datos_CMg!$C$1898:$C$1905,2) -> 150.69 | L83: =LARGE(Datos_CMg!$C$1898:$C$1905,3) -> 128.55 | M83: =LARGE(Datos_CMg!$C$1898:$C$1905,4) -> 100.33
A84: 2022-03-22 | B84: =Datos_CMg!$D$1922 -> 2022 | C84: =(SMALL(Datos_CMg!$C$1931:$C$1939,1)+SMALL(Datos_CMg!$C$1931:$C$1939,2)+SMALL(Datos_CMg!$C$1931:$C$1939,3)+SMALL(Datos_CMg!$C$1931:$C$1939,4))/4 -> 121.435 | D84: =(LARGE($F84:$M84,1)+LARGE($F84:$M84,2)+LARGE($F84:$M84,3)+LARGE($F84:$M84,4))/4 -> 235.93 | E84: =D84-C84 -> 114.495 | F84: =LARGE(Datos_CMg!$C$1941:$C$1945,1) -> 235.93 | G84: =LARGE(Datos_CMg!$C$1941:$C$1945,2) -> 235.93 | H84: =LARGE(Datos_CMg!$C$1941:$C$1945,3) -> 235.93 | I84: =LARGE(Datos_CMg!$C$1941:$C$1945,4) -> 235.93 | J84: =LARGE(Datos_CMg!$C$1922:$C$1929,1) -> 208.02 | K84: =LARGE(Datos_CMg!$C$1922:$C$1929,2) -> 89.36 | L84: =LARGE(Datos_CMg!$C$1922:$C$1929,3) -> 86.71 | M84: =LARGE(Datos_CMg!$C$1922:$C$1929,4) -> 84.28
A85: 2022-03-23 | B85: =Datos_CMg!$D$1946 -> 2022 | C85: =(SMALL(Datos_CMg!$C$1955:$C$1963,1)+SMALL(Datos_CMg!$C$1955:$C$1963,2)+SMALL(Datos_CMg!$C$1955:$C$1963,3)+SMALL(Datos_CMg!$C$1955:$C$1963,4))/4 -> 87.5 | D85: =(LARGE($F85:$M85,1)+LARGE($F85:$M85,2)+LARGE($F85:$M85,3)+LARGE($F85:$M85,4))/4 -> 129.0825 | E85: =D85-C85 -> 41.5825 | F85: =LARGE(Datos_CMg!$C$1965:$C$1969,1) -> 125.99 | G85: =LARGE(Datos_CMg!$C$1965:$C$1969,2) -> 95.9 | H85: =LARGE(Datos_CMg!$C$1965:$C$1969,3) -> 94 | I85: =LARGE(Datos_CMg!$C$1965:$C$1969,4) -> 92.78 | J85: =LARGE(Datos_CMg!$C$1946:$C$1953,1) -> 146.73 | K85: =LARGE(Datos_CMg!$C$1946:$C$1953,2) -> 133.88 | L85: =LARGE(Datos_CMg!$C$1946:$C$1953,3) -> 109.73 | M85: =LARGE(Datos_CMg!$C$1946:$C$1953,4) -> 95.1
A86: 2022-03-24 | B86: =Datos_CMg!$D$1970 -> 2022 | C86: =(SMALL(Datos_CMg!$C$1979:$C$1987,1)+SMALL(Datos_CMg!$C$1979:$C$1987,2)+SMALL(Datos_CMg!$C$1979:$C$1987,3)+SMALL(Datos_CMg!$C$1979:$C$1987,4))/4 -> 35.425 | D86: =(LARGE($F86:$M86,1)+LARGE($F86:$M86,2)+LARGE($F86:$M86,3)+LARGE($F86:$M86,4))/4 -> 136.19 | E86: =D86-C86 -> 100.765 | F86: =LARGE(Datos_CMg!$C$1989:$C$1993,1) -> 136.19 | G86: =LARGE(Datos_CMg!$C$1989:$C$1993,2) -> 136.19 | H86: =LARGE(Datos_CMg!$C$1989:$C$1993,3) -> 136.19 | I86: =LARGE(Datos_CMg!$C$1989:$C$1993,4) -> 136.19 | J86: =LARGE(Datos_CMg!$C$1970:$C$1977,1) -> 132.13 | K86: =LARGE(Datos_CMg!$C$1970:$C$1977,2) -> 108.91 | L86: =LARGE(Datos_CMg!$C$1970:$C$1977,3) -> 87.21 | M86: =LARGE(Datos_CMg!$C$1970:$C$1977,4) -> 87.1
A87: 2022-03-25 | B87: =Datos_CMg!$D$1994 -> 2022 | C87: =(SMALL(Datos_CMg!$C$2003:$C$2011,1)+SMALL(Datos_CMg!$C$2003:$C$2011,2)+SMALL(Datos_CMg!$C$2003:$C$2011,3)+SMALL(Datos_CMg!$C$2003:$C$2011,4))/4 -> 108.9025 | D87: =(LARGE($F87:$M87,1)+LARGE($F87:$M87,2)+LARGE($F87:$M87,3)+LARGE($F87:$M87,4))/4 -> 286.75 | E87: =D87-C87 -> 177.8475 | F87: =LARGE(Datos_CMg!$C$2013:$C$2017,1) -> 286.75 | G87: =LARGE(Datos_CMg!$C$2013:$C$2017,2) -> 286.75 | H87: =LARGE(Datos_CMg!$C$2013:$C$2017,3) -> 286.75 | I87: =LARGE(Datos_CMg!$C$2013:$C$2017,4) -> 286.75 | J87: =LARGE(Datos_CMg!$C$1994:$C$2001,1) -> 247.99 | K87: =LARGE(Datos_CMg!$C$1994:$C$2001,2) -> 223.37 | L87: =LARGE(Datos_CMg!$C$1994:$C$2001,3) -> 218.67 | M87: =LARGE(Datos_CMg!$C$1994:$C$2001,4) -> 99.82
A88: 2022-03-26 | B88: =Datos_CMg!$D$2018 -> 2022 | C88: =(SMALL(Datos_CMg!$C$2027:$C$2035,1)+SMALL(Datos_CMg!$C$2027:$C$2035,2)+SMALL(Datos_CMg!$C$2027:$C$2035,3)+SMALL(Datos_CMg!$C$2027:$C$2035,4))/4 -> 37.2225 | D88: =(LARGE($F88:$M88,1)+LARGE($F88:$M88,2)+LARGE($F88:$M88,3)+LARGE($F88:$M88,4))/4 -> 311.0275 | E88: =D88-C88 -> 273.805 | F88: =LARGE(Datos_CMg!$C$2037:$C$2041,1) -> 315.96 | G88: =LARGE(Datos_CMg!$C$2037:$C$2041,2) -> 315.96 | H88: =LARGE(Datos_CMg!$C$2037:$C$2041,3) -> 315.96 | I88: =LARGE(Datos_CMg!$C$2037:$C$2041,4) -> 296.23 | J88: =LARGE(Datos_CMg!$C$2018:$C$2025,1) -> 142.21 | K88: =LARGE(Datos_CMg!$C$2018:$C$2025,2) -> 142.21 | L88: =LARGE(Datos_CMg!$C$2018:$C$2025,3) -> 142.21 | M88: =LARGE(Datos_CMg!$C$2018:$C$2025,4) -> 142.21
A89: 2022-03-27 | B89: =Datos_CMg!$D$2042 -> 2022 | C89: =(SMALL(Datos_CMg!$C$2051:$C$2059,1)+SMALL(Datos_CMg!$C$2051:$C$2059,2)+SMALL(Datos_CMg!$C$2051:$C$2059,3)+SMALL(Datos_CMg!$C$2051:$C$2059,4))/4 -> 0 | D89: =(LARGE($F89:$M89,1)+LARGE($F89:$M89,2)+LARGE($F89:$M89,3)+LARGE($F89:$M89,4))/4 -> 273.995 | E89: =D89-C89 -> 273.995 | F89: =LARGE(Datos_CMg!$C$2061:$C$2065,1) -> 214.89 | G89: =LARGE(Datos_CMg!$C$2061:$C$2065,2) -> 206.78 | H89: =LARGE(Datos_CMg!$C$2061:$C$2065,3) -> 204.78 | I89: =LARGE(Datos_CMg!$C$2061:$C$2065,4) -> 117.51 | J89: =LARGE(Datos_CMg!$C$2042:$C$2049,1) -> 302 | K89: =LARGE(Datos_CMg!$C$2042:$C$2049,2) -> 290.92 | L89: =LARGE(Datos_CMg!$C$2042:$C$2049,3) -> 258.48 | M89: =LARGE(Datos_CMg!$C$2042:$C$2049,4) -> 244.58
A90: 2022-03-28 | B90: =Datos_CMg!$D$2066 -> 2022 | C90: =(SMALL(Datos_CMg!$C$2075:$C$2083,1)+SMALL(Datos_CMg!$C$2075:$C$2083,2)+SMALL(Datos_CMg!$C$2075:$C$2083,3)+SMALL(Datos_CMg!$C$2075:$C$2083,4))/4 -> 104.4775 | D90: =(LARGE($F90:$M90,1)+LARGE($F90:$M90,2)+LARGE($F90:$M90,3)+LARGE($F90:$M90,4))/4 -> 258.685 | E90: =D90-C90 -> 154.2075 | F90: =LARGE(Datos_CMg!$C$2085:$C$2089,1) -> 318.73 | G90: =LARGE(Datos_CMg!$C$2085:$C$2089,2) -> 315.09 | H90: =LARGE(Datos_CMg!$C$2085:$C$2089,3) -> 222.35 | I90: =LARGE(Datos_CMg!$C$2085:$C$2089,4) -> 178.57 | J90: =LARGE(Datos_CMg!$C$2066:$C$2073,1) -> 130.36 | K90: =LARGE(Datos_CMg!$C$2066:$C$2073,2) -> 130.36 | L90: =LARGE(Datos_CMg!$C$2066:$C$2073,3) -> 130.36 | M90: =LARGE(Datos_CMg!$C$2066:$C$2073,4) -> 129
A91: 2022-03-29 | B91: =Datos_CMg!$D$2090 -> 2022 | C91: =(SMALL(Datos_CMg!$C$2099:$C$2107,1)+SMALL(Datos_CMg!$C$2099:$C$2107,2)+SMALL(Datos_CMg!$C$2099:$C$2107,3)+SMALL(Datos_CMg!$C$2099:$C$2107,4))/4 -> 174.76 | D91: =(LARGE($F91:$M91,1)+LARGE($F91:$M91,2)+LARGE($F91:$M91,3)+LARGE($F91:$M91,4))/4 -> 286.3525 | E91: =D91-C91 -> 111.5925 | F91: =LARGE(Datos_CMg!$C$2109:$C$2113,1) -> 293.59 | G91: =LARGE(Datos_CMg!$C$2109:$C$2113,2) -> 255.01 | H91: =LARGE(Datos_CMg!$C$2109:$C$2113,3) -> 207.85 | I91: =LARGE(Datos_CMg!$C$2109:$C$2113,4) -> 144.79 | J91: =LARGE(Datos_CMg!$C$2090:$C$2097,1) -> 308.99 | K91: =LARGE(Datos_CMg!$C$2090:$C$2097,2) -> 287.82 | L91: =LARGE(Datos_CMg!$C$2090:$C$2097,3) -> 245.49 | M91: =LARGE(Datos_CMg!$C$2090:$C$2097,4) -> 220.18
A92: 2022-03-30 | B92: =Datos_CMg!$D$2114 -> 2022 | C92: =(SMALL(Datos_CMg!$C$2123:$C$2131,1)+SMALL(Datos_CMg!$C$2123:$C$2131,2)+SMALL(Datos_CMg!$C$2123:$C$2131,3)+SMALL(Datos_CMg!$C$2123:$C$2131,4))/4 -> 11.19 | D92: =(LARGE($F92:$M92,1)+LARGE($F92:$M92,2)+LARGE($F92:$M92,3)+LARGE($F92:$M92,4))/4 -> 199.9025 | E92: =D92-C92 -> 188.7125 | F92: =LARGE(Datos_CMg!$C$2133:$C$2137,1) -> 214.52 | G92: =LARGE(Datos_CMg!$C$2133:$C$2137,2) -> 214.52 | H92: =LARGE(Datos_CMg!$C$2133:$C$2137,3) -> 209.9 | I92: =LARGE(Datos_CMg!$C$2133:$C$2137,4) -> 160.67 | J92: =LARGE(Datos_CMg!$C$2114:$C$2121,1) -> 141.65 | K92: =LARGE(Datos_CMg!$C$2114:$C$2121,2) -> 141.65 | L92: =LARGE(Datos_CMg!$C$2114:$C$2121,3) -> 141.65 | M92: =LARGE(Datos_CMg!$C$2114:$C$2121,4) -> 141.65
A93: 2022-03-31 | B93: =Datos_CMg!$D$2138 -> 2022 | C93: =(SMALL(Datos_CMg!$C$2147:$C$2155,1)+SMALL(Datos_CMg!$C$2147:$C$2155,2)+SMALL(Datos_CMg!$C$2147:$C$2155,3)+SMALL(Datos_CMg!$C$2147:$C$2155,4))/4 -> 96.705 | D93: =(LARGE($F93:$M93,1)+LARGE($F93:$M93,2)+LARGE($F93:$M93,3)+LARGE($F93:$M93,4))/4 -> 151.3725 | E93: =D93-C93 -> 54.6675 | F93: =LARGE(Datos_CMg!$C$2157:$C$2161,1) -> 151.17 | G93: =LARGE(Datos_CMg!$C$2157:$C$2161,2) -> 147.76 | H93: =LARGE(Datos_CMg!$C$2157:$C$2161,3) -> 142.97 | I93: =LARGE(Datos_CMg!$C$2157:$C$2161,4) -> 139.89 | J93: =LARGE(Datos_CMg!$C$2138:$C$2145,1) -> 152.48 | K93: =LARGE(Datos_CMg!$C$2138:$C$2145,2) -> 152.48 | L93: =LARGE(Datos_CMg!$C$2138:$C$2145,3) -> 149.36 | M93: =LARGE(Datos_CMg!$C$2138:$C$2145,4) -> 143.79
A94: 2022-04-01 | B94: =Datos_CMg!$D$2162 -> 2022 | C94: =(SMALL(Datos_CMg!$C$2171:$C$2179,1)+SMALL(Datos_CMg!$C$2171:$C$2179,2)+SMALL(Datos_CMg!$C$2171:$C$2179,3)+SMALL(Datos_CMg!$C$2171:$C$2179,4))/4 -> 46.5625 | D94: =(LARGE($F94:$M94,1)+LARGE($F94:$M94,2)+LARGE($F94:$M94,3)+LARGE($F94:$M94,4))/4 -> 165.64 | E94: =D94-C94 -> 119.0775 | F94: =LARGE(Datos_CMg!$C$2181:$C$2185,1) -> 216.18 | G94: =LARGE(Datos_CMg!$C$2181:$C$2185,2) -> 167.25 | H94: =LARGE(Datos_CMg!$C$2181:$C$2185,3) -> 146.32 | I94: =LARGE(Datos_CMg!$C$2181:$C$2185,4) -> 132.81 | J94: =LARGE(Datos_CMg!$C$2162:$C$2169,1) -> 123.24 | K94: =LARGE(Datos_CMg!$C$2162:$C$2169,2) -> 104.78 | L94: =LARGE(Datos_CMg!$C$2162:$C$2169,3) -> 99.35 | M94: =LARGE(Datos_CMg!$C$2162:$C$2169,4) -> 93.29
A95: 2022-04-02 | B95: =Datos_CMg!$D$2186 -> 2022 | C95: =(SMALL(Datos_CMg!$C$2195:$C$2203,1)+SMALL(Datos_CMg!$C$2195:$C$2203,2)+SMALL(Datos_CMg!$C$2195:$C$2203,3)+SMALL(Datos_CMg!$C$2195:$C$2203,4))/4 -> 14.605 | D95: =(LARGE($F95:$M95,1)+LARGE($F95:$M95,2)+LARGE($F95:$M95,3)+LARGE($F95:$M95,4))/4 -> 235.355 | E95: =D95-C95 -> 220.75 | F95: =LARGE(Datos_CMg!$C$2205:$C$2209,1) -> 317.55 | G95: =LARGE(Datos_CMg!$C$2205:$C$2209,2) -> 215.02 | H95: =LARGE(Datos_CMg!$C$2205:$C$2209,3) -> 202.24 | I95: =LARGE(Datos_CMg!$C$2205:$C$2209,4) -> 165.83 | J95: =LARGE(Datos_CMg!$C$2186:$C$2193,1) -> 206.61 | K95: =LARGE(Datos_CMg!$C$2186:$C$2193,2) -> 161.28 | L95: =LARGE(Datos_CMg!$C$2186:$C$2193,3) -> 155.24 | M95: =LARGE(Datos_CMg!$C$2186:$C$2193,4) -> 155.24
A96: 2022-04-03 | B96: =Datos_CMg!$D$2210 -> 2022 | C96: =(SMALL(Datos_CMg!$C$2219:$C$2227,1)+SMALL(Datos_CMg!$C$2219:$C$2227,2)+SMALL(Datos_CMg!$C$2219:$C$2227,3)+SMALL(Datos_CMg!$C$2219:$C$2227,4))/4 -> 0 | D96: =(LARGE($F96:$M96,1)+LARGE($F96:$M96,2)+LARGE($F96:$M96,3)+LARGE($F96:$M96,4))/4 -> 133.8475 | E96: =D96-C96 -> 133.8475 | F96: =LARGE(Datos_CMg!$C$2229:$C$2233,1) -> 124.33 | G96: =LARGE(Datos_CMg!$C$2229:$C$2233,2) -> 124.33 | H96: =LARGE(Datos_CMg!$C$2229:$C$2233,3) -> 119.05 | I96: =LARGE(Datos_CMg!$C$2229:$C$2233,4) -> 85.54 | J96: =LARGE(Datos_CMg!$C$2210:$C$2217,1) -> 142.15 | K96: =LARGE(Datos_CMg!$C$2210:$C$2217,2) -> 142.15 | L96: =LARGE(Datos_CMg!$C$2210:$C$2217,3) -> 126.76 | M96: =LARGE(Datos_CMg!$C$2210:$C$2217,4) -> 89.56
A97: 2022-04-04 | B97: =Datos_CMg!$D$2234 -> 2022 | C97: =(SMALL(Datos_CMg!$C$2243:$C$2251,1)+SMALL(Datos_CMg!$C$2243:$C$2251,2)+SMALL(Datos_CMg!$C$2243:$C$2251,3)+SMALL(Datos_CMg!$C$2243:$C$2251,4))/4 -> 50.765 | D97: =(LARGE($F97:$M97,1)+LARGE($F97:$M97,2)+LARGE($F97:$M97,3)+LARGE($F97:$M97,4))/4 -> 143.9325 | E97: =D97-C97 -> 93.1675 | F97: =LARGE(Datos_CMg!$C$2253:$C$2257,1) -> 178.7 | G97: =LARGE(Datos_CMg!$C$2253:$C$2257,2) -> 143.42 | H97: =LARGE(Datos_CMg!$C$2253:$C$2257,3) -> 133.64 | I97: =LARGE(Datos_CMg!$C$2253:$C$2257,4) -> 119.97 | J97: =LARGE(Datos_CMg!$C$2234:$C$2241,1) -> 99.4 | K97: =LARGE(Datos_CMg!$C$2234:$C$2241,2) -> 97.55 | L97: =LARGE(Datos_CMg!$C$2234:$C$2241,3) -> 95.84 | M97: =LARGE(Datos_CMg!$C$2234:$C$2241,4) -> 87.39
A98: 2022-04-05 | B98: =Datos_CMg!$D$2258 -> 2022 | C98: =(SMALL(Datos_CMg!$C$2267:$C$2275,1)+SMALL(Datos_CMg!$C$2267:$C$2275,2)+SMALL(Datos_CMg!$C$2267:$C$2275,3)+SMALL(Datos_CMg!$C$2267:$C$2275,4))/4 -> 87.775 | D98: =(LARGE($F98:$M98,1)+LARGE($F98:$M98,2)+LARGE($F98:$M98,3)+LARGE($F98:$M98,4))/4 -> 227.255 | E98: =D98-C98 -> 139.48 | F98: =LARGE(Datos_CMg!$C$2277:$C$2281,1) -> 297.56 | G98: =LARGE(Datos_CMg!$C$2277:$C$2281,2) -> 206.65 | H98: =LARGE(Datos_CMg!$C$2277:$C$2281,3) -> 206.65 | I98: =LARGE(Datos_CMg!$C$2277:$C$2281,4) -> 198.16 | J98: =LARGE(Datos_CMg!$C$2258:$C$2265,1) -> 125.79 | K98: =LARGE(Datos_CMg!$C$2258:$C$2265,2) -> 124 | L98: =LARGE(Datos_CMg!$C$2258:$C$2265,3) -> 113.24 | M98: =LARGE(Datos_CMg!$C$2258:$C$2265,4) -> 113.15
A99: 2022-04-06 | B99: =Datos_CMg!$D$2282 -> 2022 | C99: =(SMALL(Datos_CMg!$C$2291:$C$2299,1)+SMALL(Datos_CMg!$C$2291:$C$2299,2)+SMALL(Datos_CMg!$C$2291:$C$2299,3)+SMALL(Datos_CMg!$C$2291:$C$2299,4))/4 -> 71.7475 | D99: =(LARGE($F99:$M99,1)+LARGE($F99:$M99,2)+LARGE($F99:$M99,3)+LARGE($F99:$M99,4))/4 -> 155.25 | E99: =D99-C99 -> 83.5025 | F99: =LARGE(Datos_CMg!$C$2301:$C$2305,1) -> 213.52 | G99: =LARGE(Datos_CMg!$C$2301:$C$2305,2) -> 120.04 | H99: =LARGE(Datos_CMg!$C$2301:$C$2305,3) -> 115.92 | I99: =LARGE(Datos_CMg!$C$2301:$C$2305,4) -> 112.62 | J99: =LARGE(Datos_CMg!$C$2282:$C$2289,1) -> 140.39 | K99: =LARGE(Datos_CMg!$C$2282:$C$2289,2) -> 134.12 | L99: =LARGE(Datos_CMg!$C$2282:$C$2289,3) -> 132.97 | M99: =LARGE(Datos_CMg!$C$2282:$C$2289,4) -> 118.69
A100: 2022-04-07 | B100: =Datos_CMg!$D$2306 -> 2022 | C100: =(SMALL(Datos_CMg!$C$2315:$C$2323,1)+SMALL(Datos_CMg!$C$2315:$C$2323,2)+SMALL(Datos_CMg!$C$2315:$C$2323,3)+SMALL(Datos_CMg!$C$2315:$C$2323,4))/4 -> 89.82 | D100: =(LARGE($F100:$M100,1)+LARGE($F100:$M100,2)+LARGE($F100:$M100,3)+LARGE($F100:$M100,4))/4 -> 176.1525 | E100: =D100-C100 -> 86.3325 | F100: =LARGE(Datos_CMg!$C$2325:$C$2329,1) -> 142.08 | G100: =LARGE(Datos_CMg!$C$2325:$C$2329,2) -> 142.08 | H100: =LARGE(Datos_CMg!$C$2325:$C$2329,3) -> 103.83 | I100: =LARGE(Datos_CMg!$C$2325:$C$2329,4) -> 103.83 | J100: =LARGE(Datos_CMg!$C$2306:$C$2313,1) -> 258.69 | K100: =LARGE(Datos_CMg!$C$2306:$C$2313,2) -> 160.2 | L100: =LARGE(Datos_CMg!$C$2306:$C$2313,3) -> 142.86 | M100: =LARGE(Datos_CMg!$C$2306:$C$2313,4) -> 142.86
...

Sheet Sensibilidad_PPA
A1: Sensibilidad al precio del PPA de compra (caso base 2023–2026, 4 h)
A2: El costo de carga a spot del caso base (≈15 USD/MWh) es inferior al PPA en todo el rango evaluado; el contrato destruye valor bajo cualquier precio.
A4: Precio PPA (USD/MWh) | B4: Costo carga a PPA (USD/año) | C4: Costo carga a spot (USD/año) | D4: Sobrecosto del PPA (USD/año) | E4: ¿Conviene el PPA?
A5: 22 | B5: =Supuestos!$B$16*A5 -> 144540 | C5: =Supuestos!$B$16*Resultado_Anual!$B$10 -> 101110.32 | D5: =B5-C5 -> 43429.682 | E5: =IF(D5>0,"No — destruye valor","Sí") -> No — destruye valor
A6: 25 | B6: =Supuestos!$B$16*A6 -> 164250 | C6: =Supuestos!$B$16*Resultado_Anual!$B$10 -> 101110.32 | D6: =B6-C6 -> 63139.682 | E6: =IF(D6>0,"No — destruye valor","Sí") -> No — destruye valor
A7: 28 | B7: =Supuestos!$B$16*A7 -> 183960 | C7: =Supuestos!$B$16*Resultado_Anual!$B$10 -> 101110.32 | D7: =B7-C7 -> 82849.682 | E7: =IF(D7>0,"No — destruye valor","Sí") -> No — destruye valor
A8: 31 | B8: =Supuestos!$B$16*A8 -> 203670 | C8: =Supuestos!$B$16*Resultado_Anual!$B$10 -> 101110.32 | D8: =B8-C8 -> 102559.68 | E8: =IF(D8>0,"No — destruye valor","Sí") -> No — destruye valor
A9: 34 | B9: =Supuestos!$B$16*A9 -> 223380 | C9: =Supuestos!$B$16*Resultado_Anual!$B$10 -> 101110.32 | D9: =B9-C9 -> 122269.68 | E9: =IF(D9>0,"No — destruye valor","Sí") -> No — destruye valor
A11: Costo de carga a spot = energía de carga (6.570 MWh) × precio medio de carga en banda solar (caso base 2023–2026, ≈15 USD/MWh). Sobrecosto = costo a PPA − costo a spot.
